[{"date": "2021-10-08", "open": 315, "high": 319, "low": 294.95, "close": 296.25}, {"date": "2021-10-11", "open": 298.5, "high": 298.5, "low": 285.1, "close": 293.65}, {"date": "2021-10-12", "open": 294.5, "high": 296, "low": 288.5, "close": 289.15}, {"date": "2021-10-13", "open": 289.9, "high": 294, "low": 280.3, "close": 290.1}, {"date": "2021-10-14", "open": 289, "high": 294, "low": 284, "close": 285.5}, {"date": "2021-10-15", "open": 289, "high": 294, "low": 284, "close": 285.5}, {"date": "2021-10-18", "open": 284, "high": 289.4, "low": 274.4, "close": 278.25}, {"date": "2021-10-19", "open": 280.25, "high": 280.25, "low": 272.3, "close": 277.2}, {"date": "2021-10-20", "open": 277.3, "high": 282.8, "low": 270, "close": 271.8}, {"date": "2021-10-21", "open": 275.45, "high": 279.9, "low": 269.2, "close": 275.65}, {"date": "2021-10-22", "open": 279, "high": 280.75, "low": 271.45, "close": 273.95}, {"date": "2021-10-25", "open": 279, "high": 279, "low": 247, "close": 264.15}, {"date": "2021-10-26", "open": 269.45, "high": 275, "low": 266.05, "close": 270.2}, {"date": "2021-10-27", "open": 275.45, "high": 277.9, "low": 266, "close": 268.7}, {"date": "2021-10-28", "open": 268.9, "high": 273.9, "low": 265.1, "close": 268.2}, {"date": "2021-10-29", "open": 268.3, "high": 268.35, "low": 254.15, "close": 259.9}, {"date": "2021-11-01", "open": 264.45, "high": 290, "low": 264.45, "close": 286.95}, {"date": "2021-11-02", "open": 291, "high": 295, "low": 275.55, "close": 282.15}, {"date": "2021-11-03", "open": 288.65, "high": 288.75, "low": 280, "close": 280.25}, {"date": "2021-11-04", "open": 288.65, "high": 288.75, "low": 280, "close": 280.25}, {"date": "2021-11-05", "open": 289.85, "high": 289.85, "low": 282.85, "close": 286.15}, {"date": "2021-11-08", "open": 286.5, "high": 289.95, "low": 273.8, "close": 279.1}, {"date": "2021-11-09", "open": 283, "high": 283, "low": 273.25, "close": 279.3}, {"date": "2021-11-10", "open": 284.45, "high": 285.95, "low": 277, "close": 277.7}, {"date": "2021-11-11", "open": 263.55, "high": 285.95, "low": 263.55, "close": 281.1}, {"date": "2021-11-12", "open": 281.15, "high": 283.1, "low": 272.3, "close": 276.4}, {"date": "2021-11-15", "open": 279.4, "high": 279.45, "low": 260, "close": 265.8}, {"date": "2021-11-16", "open": 260, "high": 275.95, "low": 260, "close": 269.5}, {"date": "2021-11-17", "open": 271.95, "high": 285.55, "low": 267, "close": 273.55}, {"date": "2021-11-18", "open": 276.9, "high": 288, "low": 265, "close": 283.05}, {"date": "2021-11-19", "open": 276.9, "high": 288, "low": 265, "close": 283.05}, {"date": "2021-11-22", "open": 282, "high": 286, "low": 265.4, "close": 267.45}, {"date": "2021-11-23", "open": 262.2, "high": 272, "low": 261, "close": 268.45}, {"date": "2021-11-24", "open": 274.9, "high": 278.95, "low": 266.6, "close": 273.35}, {"date": "2021-11-25", "open": 270.4, "high": 278, "low": 270, "close": 271.6}, {"date": "2021-11-26", "open": 270.5, "high": 270.6, "low": 258.1, "close": 260.75}, {"date": "2021-11-29", "open": 266, "high": 266.1, "low": 237.75, "close": 254.8}, {"date": "2021-11-30", "open": 251.45, "high": 259.8, "low": 251.4, "close": 254.45}, {"date": "2021-12-01", "open": 267.8, "high": 267.8, "low": 251.9, "close": 253.85}, {"date": "2021-12-02", "open": 258.65, "high": 301.2, "low": 252.65, "close": 288.15}, {"date": "2021-12-03", "open": 288, "high": 306, "low": 281.35, "close": 285.35}, {"date": "2021-12-06", "open": 289, "high": 289, "low": 274, "close": 279.25}, {"date": "2021-12-07", "open": 284.45, "high": 286.3, "low": 276.95, "close": 277.95}, {"date": "2021-12-08", "open": 280, "high": 281.5, "low": 275.1, "close": 275.7}, {"date": "2021-12-09", "open": 273.05, "high": 281.2, "low": 271.1, "close": 272.5}, {"date": "2021-12-10", "open": 277.45, "high": 282.1, "low": 272, "close": 278.5}, {"date": "2021-12-13", "open": 278.55, "high": 284, "low": 277.5, "close": 278.35}, {"date": "2021-12-14", "open": 282.25, "high": 283, "low": 278.4, "close": 282}, {"date": "2021-12-15", "open": 282.5, "high": 284.45, "low": 278.55, "close": 280}, {"date": "2021-12-16", "open": 281.95, "high": 304.75, "low": 277.25, "close": 290.05}, {"date": "2021-12-17", "open": 291.5, "high": 295.5, "low": 282, "close": 282.45}, {"date": "2021-12-20", "open": 282.45, "high": 282.45, "low": 270.5, "close": 275.65}, {"date": "2021-12-21", "open": 275, "high": 285.1, "low": 273.95, "close": 280.55}, {"date": "2021-12-22", "open": 281.8, "high": 284.5, "low": 276.15, "close": 279.8}, {"date": "2021-12-23", "open": 286, "high": 287, "low": 281.5, "close": 282.3}, {"date": "2021-12-24", "open": 283, "high": 288.15, "low": 275, "close": 278.9}, {"date": "2021-12-27", "open": 273, "high": 288.3, "low": 273, "close": 282.55}, {"date": "2021-12-28", "open": 276, "high": 299, "low": 276, "close": 291.7}, {"date": "2021-12-29", "open": 297.2, "high": 299.65, "low": 286.2, "close": 290.7}, {"date": "2021-12-30", "open": 296.1, "high": 311, "low": 292, "close": 308.75}, {"date": "2021-12-31", "open": 312.9, "high": 333.85, "low": 305, "close": 319.15}, {"date": "2022-01-03", "open": 317.2, "high": 343.35, "low": 315.7, "close": 328.7}, {"date": "2022-01-04", "open": 331.25, "high": 331.25, "low": 316.4, "close": 325.65}, {"date": "2022-01-05", "open": 328.7, "high": 328.7, "low": 315, "close": 317.45}, {"date": "2022-01-06", "open": 317.45, "high": 325.45, "low": 310, "close": 320.1}, {"date": "2022-01-07", "open": 322.7, "high": 323, "low": 299.25, "close": 304.8}, {"date": "2022-01-10", "open": 310, "high": 329.3, "low": 306.45, "close": 324.9}, {"date": "2022-01-11", "open": 326, "high": 327.2, "low": 311.05, "close": 317.25}, {"date": "2022-01-12", "open": 320.8, "high": 334.3, "low": 317.05, "close": 324}, {"date": "2022-01-13", "open": 324.95, "high": 388.8, "low": 323, "close": 388.8}, {"date": "2022-01-14", "open": 445, "high": 466.55, "low": 432, "close": 466.55}, {"date": "2022-01-17", "open": 475, "high": 513.2, "low": 466.55, "close": 513.2}, {"date": "2022-01-18", "open": 537, "high": 564.5, "low": 471, "close": 478.1}, {"date": "2022-01-19", "open": 465, "high": 488, "low": 445.2, "close": 473.45}, {"date": "2022-01-20", "open": 471.6, "high": 498.4, "low": 471.6, "close": 492.55}, {"date": "2022-01-21", "open": 478.1, "high": 494, "low": 461, "close": 469.2}, {"date": "2022-01-24", "open": 471, "high": 489, "low": 448, "close": 479.15}, {"date": "2022-01-25", "open": 484.95, "high": 495, "low": 462.65, "close": 474.2}, {"date": "2022-01-26", "open": 484.95, "high": 495, "low": 462.65, "close": 474.2}, {"date": "2022-01-27", "open": 456, "high": 478.3, "low": 455, "close": 459.4}, {"date": "2022-01-28", "open": 451, "high": 464, "low": 449.15, "close": 450.85}, {"date": "2022-01-31", "open": 460, "high": 462.35, "low": 443.2, "close": 446.1}, {"date": "2022-02-01", "open": 449.8, "high": 490.7, "low": 428.95, "close": 490.7}, {"date": "2022-02-02", "open": 504, "high": 508.7, "low": 470.4, "close": 473.35}, {"date": "2022-02-03", "open": 475, "high": 490, "low": 468.2, "close": 471.65}, {"date": "2022-02-04", "open": 470, "high": 472, "low": 462.6, "close": 464.15}, {"date": "2022-02-07", "open": 465, "high": 475.25, "low": 450.15, "close": 455.75}, {"date": "2022-02-08", "open": 457, "high": 463.1, "low": 428.1, "close": 440.7}, {"date": "2022-02-09", "open": 447.5, "high": 472.7, "low": 446.7, "close": 462.65}, {"date": "2022-02-10", "open": 468, "high": 470, "low": 461.2, "close": 465.7}, {"date": "2022-02-11", "open": 465.3, "high": 468.15, "low": 372.6, "close": 392.45}, {"date": "2022-02-14", "open": 375.5, "high": 418, "low": 374.5, "close": 401.6}, {"date": "2022-02-15", "open": 401.6, "high": 402.7, "low": 370.15, "close": 386.9}, {"date": "2022-02-16", "open": 390, "high": 399.55, "low": 350.1, "close": 366.1}, {"date": "2022-02-17", "open": 370, "high": 382.75, "low": 367.8, "close": 370.3}, {"date": "2022-02-18", "open": 370.3, "high": 371.5, "low": 364.15, "close": 366}, {"date": "2022-02-21", "open": 369, "high": 369, "low": 345.55, "close": 352.15}, {"date": "2022-02-22", "open": 346, "high": 346.65, "low": 330, "close": 337.05}, {"date": "2022-02-23", "open": 349, "high": 402, "low": 343, "close": 367.45}, {"date": "2022-02-24", "open": 350.1, "high": 359.8, "low": 331, "close": 336.05}, {"date": "2022-02-25", "open": 374, "high": 374, "low": 351.45, "close": 354.95}, {"date": "2022-02-28", "open": 345, "high": 376.5, "low": 336.1, "close": 374.5}, {"date": "2022-03-01", "open": 345, "high": 376.5, "low": 336.1, "close": 374.5}, {"date": "2022-03-02", "open": 373.45, "high": 385, "low": 363.05, "close": 377.05}, {"date": "2022-03-03", "open": 377.2, "high": 384.9, "low": 363.15, "close": 366.4}, {"date": "2022-03-04", "open": 366.4, "high": 371.65, "low": 359.2, "close": 361.9}, {"date": "2022-03-07", "open": 361.4, "high": 364, "low": 345.05, "close": 354}, {"date": "2022-03-08", "open": 345.05, "high": 375, "low": 345.05, "close": 366.35}, {"date": "2022-03-09", "open": 370, "high": 379.85, "low": 357, "close": 374.25}, {"date": "2022-03-10", "open": 385, "high": 387.35, "low": 368.15, "close": 372.65}, {"date": "2022-03-11", "open": 376.95, "high": 376.95, "low": 353.75, "close": 360.1}, {"date": "2022-03-14", "open": 365.55, "high": 373, "low": 352.75, "close": 356.6}, {"date": "2022-03-15", "open": 360.2, "high": 362, "low": 351.05, "close": 354.3}, {"date": "2022-03-16", "open": 358.05, "high": 367.95, "low": 356.15, "close": 363}, {"date": "2022-03-17", "open": 372, "high": 405, "low": 368.95, "close": 383.15}, {"date": "2022-03-18", "open": 372, "high": 405, "low": 368.95, "close": 383.15}, {"date": "2022-03-21", "open": 386.8, "high": 402, "low": 382.55, "close": 384.65}, {"date": "2022-03-22", "open": 384, "high": 386.65, "low": 372.45, "close": 376.65}, {"date": "2022-03-23", "open": 379.9, "high": 384.3, "low": 371.15, "close": 373}, {"date": "2022-03-24", "open": 375.75, "high": 381.65, "low": 365, "close": 367.95}, {"date": "2022-03-25", "open": 378, "high": 378, "low": 360, "close": 366.45}, {"date": "2022-03-28", "open": 363, "high": 365.3, "low": 350.1, "close": 352.05}, {"date": "2022-03-29", "open": 358.85, "high": 360.55, "low": 340.1, "close": 343.3}, {"date": "2022-03-30", "open": 359.75, "high": 367.8, "low": 352.5, "close": 360.65}, {"date": "2022-03-31", "open": 360.65, "high": 365.6, "low": 352, "close": 353.8}, {"date": "2022-04-01", "open": 361.5, "high": 367.4, "low": 355.3, "close": 359.5}, {"date": "2022-04-04", "open": 357.5, "high": 370.25, "low": 357.5, "close": 368.4}, {"date": "2022-04-05", "open": 374, "high": 402.75, "low": 366.7, "close": 395.2}, {"date": "2022-04-06", "open": 402.65, "high": 444, "low": 400, "close": 419.65}, {"date": "2022-04-07", "open": 419.8, "high": 419.9, "low": 400.1, "close": 401.25}, {"date": "2022-04-08", "open": 406, "high": 406.65, "low": 392.5, "close": 400.15}, {"date": "2022-04-11", "open": 399.75, "high": 411.1, "low": 399.75, "close": 405.2}, {"date": "2022-04-12", "open": 406.9, "high": 406.9, "low": 390.25, "close": 393.8}, {"date": "2022-04-13", "open": 403, "high": 404, "low": 392, "close": 397.95}, {"date": "2022-04-14", "open": 403, "high": 404, "low": 392, "close": 397.95}, {"date": "2022-04-15", "open": 403, "high": 404, "low": 392, "close": 397.95}, {"date": "2022-04-18", "open": 398.8, "high": 399, "low": 391.2, "close": 393.85}, {"date": "2022-04-19", "open": 401, "high": 402.35, "low": 379, "close": 384.55}, {"date": "2022-04-20", "open": 388.7, "high": 394.4, "low": 342, "close": 379.35}, {"date": "2022-04-21", "open": 379.85, "high": 419, "low": 375.4, "close": 414.6}, {"date": "2022-04-22", "open": 414.6, "high": 432, "low": 409.75, "close": 415.5}, {"date": "2022-04-25", "open": 414.95, "high": 418, "low": 392.8, "close": 396.75}, {"date": "2022-04-26", "open": 397.05, "high": 408, "low": 385.25, "close": 386.45}, {"date": "2022-04-27", "open": 386.9, "high": 391, "low": 376, "close": 388.85}, {"date": "2022-04-28", "open": 382.85, "high": 394.55, "low": 378, "close": 380.7}, {"date": "2022-04-29", "open": 385, "high": 391.45, "low": 373, "close": 375.7}, {"date": "2022-05-02", "open": 363, "high": 375.45, "low": 362.8, "close": 366.45}, {"date": "2022-05-03", "open": 363, "high": 375.45, "low": 362.8, "close": 366.45}, {"date": "2022-05-04", "open": 369, "high": 374.95, "low": 355.1, "close": 358.7}, {"date": "2022-05-05", "open": 359, "high": 382, "low": 355.05, "close": 376.05}, {"date": "2022-05-06", "open": 375, "high": 375, "low": 351.5, "close": 358.4}, {"date": "2022-05-09", "open": 346, "high": 354.7, "low": 345, "close": 347.25}, {"date": "2022-05-10", "open": 348, "high": 355, "low": 336.1, "close": 340.7}, {"date": "2022-05-11", "open": 340.7, "high": 347.55, "low": 302.45, "close": 311.55}, {"date": "2022-05-12", "open": 296, "high": 328, "low": 291.25, "close": 311.65}, {"date": "2022-05-13", "open": 325.65, "high": 329.65, "low": 311, "close": 313.65}, {"date": "2022-05-16", "open": 327, "high": 329.55, "low": 317.05, "close": 323.8}, {"date": "2022-05-17", "open": 330, "high": 330, "low": 322, "close": 326.4}, {"date": "2022-05-18", "open": 333.75, "high": 338.05, "low": 326, "close": 327.75}, {"date": "2022-05-19", "open": 325, "high": 325.95, "low": 313.2, "close": 314.4}, {"date": "2022-05-20", "open": 316.05, "high": 321.3, "low": 311, "close": 313.45}, {"date": "2022-05-23", "open": 313.45, "high": 317.1, "low": 301.1, "close": 307.55}, {"date": "2022-05-24", "open": 313.55, "high": 314.95, "low": 301, "close": 303.5}, {"date": "2022-05-25", "open": 307, "high": 307, "low": 282, "close": 284.9}, {"date": "2022-05-26", "open": 297.8, "high": 299.8, "low": 270.05, "close": 275.45}, {"date": "2022-05-27", "open": 283.85, "high": 298.7, "low": 283, "close": 294.05}, {"date": "2022-05-30", "open": 295.15, "high": 304.8, "low": 279.4, "close": 282.45}, {"date": "2022-05-31", "open": 273.1, "high": 274, "low": 249.55, "close": 264.45}, {"date": "2022-06-01", "open": 265, "high": 273, "low": 264.55, "close": 270.3}, {"date": "2022-06-02", "open": 273, "high": 281.65, "low": 269, "close": 277.8}, {"date": "2022-06-03", "open": 279.5, "high": 283.95, "low": 266, "close": 269.95}, {"date": "2022-06-06", "open": 266, "high": 269.1, "low": 263, "close": 263.5}, {"date": "2022-06-07", "open": 266.6, "high": 269.6, "low": 263.5, "close": 265.55}, {"date": "2022-06-08", "open": 273.95, "high": 273.95, "low": 261.2, "close": 262.5}, {"date": "2022-06-09", "open": 266.9, "high": 269.95, "low": 262.55, "close": 266.25}, {"date": "2022-06-10", "open": 265.85, "high": 274, "low": 264.65, "close": 273}, {"date": "2022-06-13", "open": 269, "high": 270, "low": 260.1, "close": 263}, {"date": "2022-06-14", "open": 264.95, "high": 268.45, "low": 260.15, "close": 261.85}, {"date": "2022-06-15", "open": 265.8, "high": 274.9, "low": 262, "close": 272.95}, {"date": "2022-06-16", "open": 274, "high": 275, "low": 255, "close": 257.2}, {"date": "2022-06-17", "open": 262, "high": 263.95, "low": 249.5, "close": 251.9}, {"date": "2022-06-20", "open": 253.15, "high": 254.25, "low": 240.05, "close": 243}, {"date": "2022-06-21", "open": 251.9, "high": 255.55, "low": 244, "close": 253.9}, {"date": "2022-06-22", "open": 252.8, "high": 254.9, "low": 246.05, "close": 252.55}, {"date": "2022-06-23", "open": 252.7, "high": 265.1, "low": 252.55, "close": 263.1}, {"date": "2022-06-24", "open": 266.9, "high": 272.6, "low": 264.5, "close": 270.05}, {"date": "2022-06-27", "open": 274.95, "high": 280, "low": 271, "close": 272.15}, {"date": "2022-06-28", "open": 270.25, "high": 276.75, "low": 260.25, "close": 267}, {"date": "2022-06-29", "open": 266.9, "high": 269.45, "low": 262.25, "close": 263.25}, {"date": "2022-06-30", "open": 267, "high": 272.05, "low": 260.1, "close": 261.7}, {"date": "2022-07-01", "open": 264, "high": 264, "low": 257.45, "close": 259.85}, {"date": "2022-07-04", "open": 262.45, "high": 270, "low": 252.1, "close": 258.35}, {"date": "2022-07-05", "open": 260, "high": 264.85, "low": 249, "close": 252.15}, {"date": "2022-07-06", "open": 255, "high": 255, "low": 248.95, "close": 251.15}, {"date": "2022-07-07", "open": 255, "high": 260, "low": 251.35, "close": 255.95}, {"date": "2022-07-08", "open": 258.2, "high": 263, "low": 246.05, "close": 253.3}, {"date": "2022-07-11", "open": 257.8, "high": 303.95, "low": 250.6, "close": 303.95}, {"date": "2022-07-12", "open": 315, "high": 325, "low": 290.9, "close": 292.7}, {"date": "2022-07-13", "open": 296.95, "high": 296.95, "low": 280, "close": 282.25}, {"date": "2022-07-14", "open": 280.15, "high": 284.7, "low": 276.95, "close": 280.45}, {"date": "2022-07-15", "open": 281.65, "high": 323, "low": 281.65, "close": 312.75}, {"date": "2022-07-18", "open": 316.8, "high": 331, "low": 312.3, "close": 317.5}, {"date": "2022-07-19", "open": 316, "high": 320.05, "low": 312.95, "close": 316.65}, {"date": "2022-07-20", "open": 315, "high": 321, "low": 305, "close": 307.65}, {"date": "2022-07-21", "open": 305.25, "high": 322, "low": 304.65, "close": 317.2}, {"date": "2022-07-22", "open": 323.45, "high": 324, "low": 313.05, "close": 315.45}, {"date": "2022-07-25", "open": 324, "high": 324, "low": 308.2, "close": 309.55}, {"date": "2022-07-26", "open": 315, "high": 315, "low": 290.25, "close": 294.3}, {"date": "2022-07-27", "open": 294, "high": 302, "low": 289.85, "close": 298.4}, {"date": "2022-07-28", "open": 306.9, "high": 306.9, "low": 286, "close": 287.5}, {"date": "2022-07-29", "open": 293, "high": 294.4, "low": 285.7, "close": 288.3}, {"date": "2022-08-01", "open": 300, "high": 345.95, "low": 299, "close": 345.95}, {"date": "2022-08-02", "open": 347, "high": 356, "low": 326.25, "close": 329.15}, {"date": "2022-08-03", "open": 328.05, "high": 342.85, "low": 321.1, "close": 330.75}, {"date": "2022-08-04", "open": 333.9, "high": 336.8, "low": 316, "close": 319.25}, {"date": "2022-08-05", "open": 323.95, "high": 324.05, "low": 316.4, "close": 318}, {"date": "2022-08-10", "open": 350, "high": 350, "low": 334.55, "close": 341}, {"date": "2022-08-11", "open": 340, "high": 340.75, "low": 324.05, "close": 334.45}, {"date": "2022-08-12", "open": 339.7, "high": 365.7, "low": 330, "close": 346.45}, {"date": "2022-08-15", "open": 339.7, "high": 365.7, "low": 330, "close": 346.45}, {"date": "2022-08-16", "open": 350, "high": 350, "low": 336.3, "close": 338.7}, {"date": "2022-08-17", "open": 342.7, "high": 344, "low": 330, "close": 339.7}, {"date": "2022-08-18", "open": 344, "high": 344, "low": 330, "close": 331.6}, {"date": "2022-08-19", "open": 338.75, "high": 347.5, "low": 325, "close": 329.15}, {"date": "2022-08-22", "open": 327.85, "high": 334, "low": 322, "close": 326.6}, {"date": "2022-08-23", "open": 330, "high": 357.75, "low": 330, "close": 356.25}, {"date": "2022-08-24", "open": 360, "high": 372, "low": 346, "close": 353.9}, {"date": "2022-08-25", "open": 338, "high": 348.15, "low": 336, "close": 343.55}, {"date": "2022-08-26", "open": 350, "high": 369.9, "low": 344.55, "close": 365.3}, {"date": "2022-08-29", "open": 345.2, "high": 374.5, "low": 345.2, "close": 367.8}, {"date": "2022-08-30", "open": 368.9, "high": 374.75, "low": 359.25, "close": 370.75}, {"date": "2022-08-31", "open": 368.9, "high": 374.75, "low": 359.25, "close": 370.75}, {"date": "2022-09-01", "open": 372.5, "high": 374.6, "low": 360.05, "close": 361.5}, {"date": "2022-09-02", "open": 362, "high": 370, "low": 356, "close": 356.9}, {"date": "2022-09-05", "open": 356.9, "high": 356.9, "low": 348, "close": 351.8}, {"date": "2022-09-06", "open": 357, "high": 365.15, "low": 352.85, "close": 354.8}, {"date": "2022-09-07", "open": 354.8, "high": 359.35, "low": 346, "close": 347.75}, {"date": "2022-09-08", "open": 358, "high": 368, "low": 349.2, "close": 352.15}, {"date": "2022-09-09", "open": 357.95, "high": 357.95, "low": 347.45, "close": 350.55}, {"date": "2022-09-12", "open": 357, "high": 377, "low": 353.1, "close": 369.05}, {"date": "2022-09-13", "open": 373.8, "high": 377.7, "low": 363.35, "close": 366.1}, {"date": "2022-09-14", "open": 360, "high": 366, "low": 358.05, "close": 361.35}, {"date": "2022-09-15", "open": 369, "high": 369, "low": 352, "close": 355.9}, {"date": "2022-09-16", "open": 355.9, "high": 360.95, "low": 343, "close": 346.65}, {"date": "2022-09-19", "open": 347.6, "high": 353, "low": 327.2, "close": 329.3}, {"date": "2022-09-20", "open": 332.9, "high": 339, "low": 330.2, "close": 332.3}, {"date": "2022-09-21", "open": 335, "high": 338.25, "low": 322.85, "close": 325.45}, {"date": "2022-09-22", "open": 325.55, "high": 336.05, "low": 325, "close": 333.85}, {"date": "2022-09-23", "open": 335, "high": 339.3, "low": 323, "close": 333.55}, {"date": "2022-09-26", "open": 333.55, "high": 333.55, "low": 305, "close": 310.85}, {"date": "2022-09-27", "open": 317, "high": 324, "low": 304, "close": 306.2}, {"date": "2022-09-28", "open": 297, "high": 331.9, "low": 297, "close": 321.4}, {"date": "2022-09-29", "open": 328.85, "high": 332.9, "low": 323.1, "close": 328.9}, {"date": "2022-09-30", "open": 323, "high": 328, "low": 321.35, "close": 323.25}, {"date": "2022-10-03", "open": 322.05, "high": 347.8, "low": 322.05, "close": 340.15}, {"date": "2022-10-04", "open": 346.95, "high": 347, "low": 335.6, "close": 337.4}, {"date": "2022-10-05", "open": 346.95, "high": 347, "low": 335.6, "close": 337.4}, {"date": "2022-10-06", "open": 344, "high": 348.2, "low": 336.35, "close": 338.6}, {"date": "2022-10-07", "open": 341, "high": 346.85, "low": 338, "close": 340.95}, {"date": "2022-10-10", "open": 335, "high": 335, "low": 317, "close": 320.65}, {"date": "2022-10-11", "open": 321, "high": 335, "low": 320.65, "close": 323.55}, {"date": "2022-10-12", "open": 328.95, "high": 328.95, "low": 315, "close": 318.35}, {"date": "2022-10-13", "open": 324, "high": 324, "low": 309.6, "close": 313.25}, {"date": "2022-10-14", "open": 319.45, "high": 323.95, "low": 311.7, "close": 314.9}, {"date": "2022-10-17", "open": 307.6, "high": 319.85, "low": 307.6, "close": 316.2}, {"date": "2022-10-18", "open": 319.8, "high": 327.2, "low": 317.05, "close": 319.95}, {"date": "2022-10-19", "open": 326.25, "high": 330, "low": 309, "close": 310.8}, {"date": "2022-10-20", "open": 315.6, "high": 315.6, "low": 304, "close": 309.45}, {"date": "2022-10-21", "open": 308.9, "high": 312.6, "low": 304.2, "close": 306.95}, {"date": "2022-10-24", "open": 309.95, "high": 314.4, "low": 294, "close": 310.25}, {"date": "2022-10-25", "open": 309.9, "high": 310, "low": 301.2, "close": 305.75}, {"date": "2022-10-26", "open": 309.9, "high": 310, "low": 301.2, "close": 305.75}, {"date": "2022-10-27", "open": 302.1, "high": 308, "low": 300, "close": 307.05}, {"date": "2022-10-28", "open": 312.45, "high": 315, "low": 303, "close": 307.4}, {"date": "2022-10-31", "open": 307.35, "high": 308.9, "low": 274.1, "close": 284.5}, {"date": "2022-11-01", "open": 290.8, "high": 295.65, "low": 286.25, "close": 288.4}, {"date": "2022-11-02", "open": 290.1, "high": 291, "low": 281.2, "close": 282.5}, {"date": "2022-11-03", "open": 282.5, "high": 284.25, "low": 275, "close": 277.05}, {"date": "2022-11-04", "open": 273.5, "high": 284.55, "low": 271.8, "close": 273.65}, {"date": "2022-11-07", "open": 273.65, "high": 278.95, "low": 272.5, "close": 273.2}, {"date": "2022-11-08", "open": 273.65, "high": 278.95, "low": 272.5, "close": 273.2}, {"date": "2022-11-09", "open": 278.2, "high": 279.9, "low": 272.55, "close": 273.9}, {"date": "2022-11-10", "open": 271.1, "high": 273.9, "low": 265.55, "close": 267.5}, {"date": "2022-11-11", "open": 274.35, "high": 274.35, "low": 265, "close": 270.4}, {"date": "2022-11-14", "open": 270.4, "high": 270.4, "low": 259.65, "close": 262.25}, {"date": "2022-11-15", "open": 265.8, "high": 274.05, "low": 263.3, "close": 270.25}, {"date": "2022-11-16", "open": 273.7, "high": 273.7, "low": 262, "close": 263.3}, {"date": "2022-11-17", "open": 265, "high": 273, "low": 258, "close": 267.85}, {"date": "2022-11-18", "open": 280.1, "high": 283.95, "low": 266.6, "close": 270.6}, {"date": "2022-11-21", "open": 274.45, "high": 275, "low": 268, "close": 270.65}, {"date": "2022-11-22", "open": 273.5, "high": 273.5, "low": 261, "close": 262.4}, {"date": "2022-11-23", "open": 268.35, "high": 268.35, "low": 261.2, "close": 261.45}, {"date": "2022-11-24", "open": 262.25, "high": 267.45, "low": 260, "close": 261.6}, {"date": "2022-11-25", "open": 262.25, "high": 264.2, "low": 260, "close": 261.7}, {"date": "2022-11-28", "open": 261.7, "high": 266.95, "low": 260.55, "close": 261.7}, {"date": "2022-11-29", "open": 263.8, "high": 264, "low": 255.55, "close": 260.95}, {"date": "2022-11-30", "open": 261, "high": 261.5, "low": 256.8, "close": 258.5}, {"date": "2022-12-01", "open": 259, "high": 264.45, "low": 253.7, "close": 258.55}, {"date": "2022-12-02", "open": 258.05, "high": 271, "low": 254.5, "close": 268.65}, {"date": "2022-12-05", "open": 271, "high": 272.3, "low": 265.75, "close": 266.45}, {"date": "2022-12-06", "open": 267.35, "high": 269.35, "low": 261, "close": 262.7}, {"date": "2022-12-07", "open": 265, "high": 265, "low": 259.05, "close": 263.15}, {"date": "2022-12-08", "open": 264.85, "high": 271.25, "low": 263.05, "close": 267.8}, {"date": "2022-12-09", "open": 267.8, "high": 269.8, "low": 263.15, "close": 265}, {"date": "2022-12-12", "open": 269.8, "high": 269.8, "low": 260.1, "close": 261.6}, {"date": "2022-12-13", "open": 262, "high": 262.15, "low": 255, "close": 256.5}, {"date": "2022-12-14", "open": 259.9, "high": 260.9, "low": 256.6, "close": 257.6}, {"date": "2022-12-15", "open": 259.4, "high": 266.15, "low": 258.2, "close": 261.6}, {"date": "2022-12-16", "open": 261, "high": 261.6, "low": 254.1, "close": 255.95}, {"date": "2022-12-19", "open": 252.5, "high": 259.45, "low": 252.5, "close": 254.3}, {"date": "2022-12-20", "open": 254.5, "high": 255.8, "low": 249, "close": 251.5}, {"date": "2022-12-21", "open": 253.95, "high": 254.45, "low": 245.5, "close": 246.25}, {"date": "2022-12-22", "open": 247, "high": 247, "low": 235, "close": 237.1}, {"date": "2022-12-23", "open": 237.15, "high": 237.85, "low": 215.3, "close": 225.2}, {"date": "2022-12-26", "open": 222.5, "high": 243.2, "low": 222.5, "close": 236.85}, {"date": "2022-12-27", "open": 239.45, "high": 247, "low": 234.05, "close": 243.15}, {"date": "2022-12-28", "open": 245, "high": 245, "low": 231.3, "close": 235.1}, {"date": "2022-12-29", "open": 239.7, "high": 239.95, "low": 232.05, "close": 235.25}, {"date": "2022-12-30", "open": 238.9, "high": 241.15, "low": 236.1, "close": 238.35}, {"date": "2023-01-02", "open": 242.9, "high": 242.9, "low": 235.65, "close": 237.2}, {"date": "2023-01-03", "open": 241, "high": 241, "low": 234.4, "close": 235.65}, {"date": "2023-01-04", "open": 235.25, "high": 237.85, "low": 230.1, "close": 231.9}, {"date": "2023-01-05", "open": 234.8, "high": 234.8, "low": 231.5, "close": 232.9}, {"date": "2023-01-06", "open": 231.85, "high": 235.8, "low": 230, "close": 233.45}, {"date": "2023-01-09", "open": 236.25, "high": 241.65, "low": 230.9, "close": 232}, {"date": "2023-01-10", "open": 234.8, "high": 238.2, "low": 231.05, "close": 237.3}, {"date": "2023-01-11", "open": 238.5, "high": 238.5, "low": 232.45, "close": 233.45}, {"date": "2023-01-12", "open": 231.5, "high": 239.9, "low": 231.5, "close": 237.35}, {"date": "2023-01-13", "open": 237.35, "high": 239.45, "low": 231, "close": 234.75}, {"date": "2023-01-16", "open": 233.5, "high": 239.55, "low": 233.5, "close": 237.7}, {"date": "2023-01-17", "open": 239.5, "high": 240.4, "low": 231, "close": 232.05}, {"date": "2023-01-18", "open": 232.3, "high": 235, "low": 225, "close": 225.5}, {"date": "2023-01-19", "open": 229.9, "high": 229.9, "low": 224, "close": 225.05}, {"date": "2023-01-20", "open": 225.55, "high": 229.45, "low": 224.05, "close": 227}, {"date": "2023-01-23", "open": 226, "high": 229.95, "low": 218, "close": 219.65}, {"date": "2023-01-24", "open": 223.9, "high": 223.9, "low": 209.55, "close": 211.5}, {"date": "2023-01-25", "open": 215.6, "high": 215.6, "low": 208, "close": 211.65}, {"date": "2023-01-26", "open": 215.6, "high": 215.6, "low": 208, "close": 211.65}, {"date": "2023-01-27", "open": 210.2, "high": 217.35, "low": 207.55, "close": 213.9}, {"date": "2023-01-30", "open": 213.9, "high": 215, "low": 208.7, "close": 209.15}, {"date": "2023-01-31", "open": 213.25, "high": 213.7, "low": 207.9, "close": 209.85}, {"date": "2023-02-01", "open": 209.85, "high": 251.8, "low": 209.85, "close": 223.7}, {"date": "2023-02-02", "open": 228, "high": 237.8, "low": 224.25, "close": 227.05}, {"date": "2023-02-03", "open": 225.05, "high": 228.65, "low": 215, "close": 220.3}, {"date": "2023-02-06", "open": 226.05, "high": 227.8, "low": 216, "close": 225.15}, {"date": "2023-02-07", "open": 225.5, "high": 240, "low": 222, "close": 236.2}, {"date": "2023-02-08", "open": 232.7, "high": 245.25, "low": 232.7, "close": 240.85}, {"date": "2023-02-09", "open": 240.85, "high": 261, "low": 240, "close": 252.1}, {"date": "2023-02-10", "open": 254.8, "high": 263.1, "low": 253.65, "close": 254.95}, {"date": "2023-02-13", "open": 255.85, "high": 255.85, "low": 240, "close": 240.65}, {"date": "2023-02-14", "open": 244.25, "high": 245.8, "low": 225, "close": 227.8}, {"date": "2023-02-15", "open": 225, "high": 226, "low": 214.45, "close": 215.3}, {"date": "2023-02-16", "open": 217.9, "high": 223.45, "low": 217.75, "close": 220.4}, {"date": "2023-02-17", "open": 223.7, "high": 225.4, "low": 208.5, "close": 212.55}, {"date": "2023-02-20", "open": 214.8, "high": 216.7, "low": 210.5, "close": 215.3}, {"date": "2023-02-21", "open": 217.9, "high": 217.9, "low": 213.65, "close": 215.5}, {"date": "2023-02-22", "open": 215.4, "high": 215.5, "low": 210.05, "close": 211.1}, {"date": "2023-02-23", "open": 212, "high": 214.45, "low": 208.7, "close": 210.3}, {"date": "2023-02-24", "open": 210.3, "high": 219.9, "low": 209.35, "close": 213.35}, {"date": "2023-02-27", "open": 215.5, "high": 216.5, "low": 208.7, "close": 211}, {"date": "2023-02-28", "open": 210.5, "high": 217.45, "low": 203.9, "close": 215}, {"date": "2023-03-01", "open": 211, "high": 223.3, "low": 211, "close": 221.95}, {"date": "2023-03-02", "open": 221.95, "high": 223.95, "low": 216.3, "close": 217.5}, {"date": "2023-03-03", "open": 219.75, "high": 219.75, "low": 211.35, "close": 217.05}, {"date": "2023-03-06", "open": 219.95, "high": 230.4, "low": 213.85, "close": 225}, {"date": "2023-03-07", "open": 219.95, "high": 230.4, "low": 213.85, "close": 225}, {"date": "2023-03-08", "open": 225, "high": 225, "low": 216.15, "close": 217.3}, {"date": "2023-03-09", "open": 227, "high": 227, "low": 217, "close": 218}, {"date": "2023-03-10", "open": 215.25, "high": 221, "low": 212.5, "close": 217.6}, {"date": "2023-03-13", "open": 216, "high": 216.95, "low": 210, "close": 210.9}, {"date": "2023-03-14", "open": 210.9, "high": 213, "low": 205.55, "close": 208}, {"date": "2023-03-15", "open": 208.15, "high": 209.95, "low": 206, "close": 206.35}, {"date": "2023-03-16", "open": 210.5, "high": 210.5, "low": 203, "close": 205.25}, {"date": "2023-03-17", "open": 207.9, "high": 210.25, "low": 201, "close": 202.4}, {"date": "2023-03-20", "open": 205, "high": 205, "low": 198.15, "close": 199.95}, {"date": "2023-03-21", "open": 200, "high": 205, "low": 200, "close": 200.95}, {"date": "2023-03-22", "open": 201.9, "high": 207, "low": 201.2, "close": 202.05}, {"date": "2023-03-23", "open": 202.05, "high": 204.05, "low": 193.3, "close": 195}, {"date": "2023-03-24", "open": 198.45, "high": 198.45, "low": 178, "close": 180.15}, {"date": "2023-03-27", "open": 184.9, "high": 184.9, "low": 170, "close": 171.3}, {"date": "2023-03-28", "open": 172.8, "high": 183.5, "low": 165.9, "close": 180.1}, {"date": "2023-03-29", "open": 180.1, "high": 181.7, "low": 174, "close": 178}, {"date": "2023-03-30", "open": 180.1, "high": 181.7, "low": 174, "close": 178}, {"date": "2023-03-31", "open": 178.5, "high": 201.05, "low": 170.95, "close": 176.05}, {"date": "2023-04-03", "open": 176.8, "high": 192.65, "low": 176.5, "close": 189.35}, {"date": "2023-04-04", "open": 176.8, "high": 192.65, "low": 176.5, "close": 189.35}, {"date": "2023-04-05", "open": 191, "high": 199, "low": 189.6, "close": 195.15}, {"date": "2023-04-06", "open": 194.5, "high": 197.85, "low": 191.3, "close": 195.9}, {"date": "2023-04-07", "open": 194.5, "high": 197.85, "low": 191.3, "close": 195.9}, {"date": "2023-04-10", "open": 196, "high": 200, "low": 192.5, "close": 194.95}, {"date": "2023-04-11", "open": 195.95, "high": 197.95, "low": 192.5, "close": 196.45}, {"date": "2023-04-12", "open": 196.45, "high": 196.45, "low": 192.75, "close": 193.65}, {"date": "2023-04-13", "open": 193.2, "high": 196, "low": 192, "close": 192.5}, {"date": "2023-04-14", "open": 193.2, "high": 196, "low": 192, "close": 192.5}, {"date": "2023-04-17", "open": 198.75, "high": 199, "low": 192.9, "close": 196.55}, {"date": "2023-04-18", "open": 198.9, "high": 209.5, "low": 195.05, "close": 206.25}, {"date": "2023-04-19", "open": 213.25, "high": 219, "low": 205.05, "close": 212.9}, {"date": "2023-04-20", "open": 218, "high": 218, "low": 206.4, "close": 208.05}, {"date": "2023-04-21", "open": 209.15, "high": 209.6, "low": 204, "close": 209.05}, {"date": "2023-04-24", "open": 210, "high": 210, "low": 197, "close": 198.7}, {"date": "2023-04-25", "open": 204.9, "high": 204.9, "low": 198.4, "close": 201.55}, {"date": "2023-04-26", "open": 202, "high": 208.9, "low": 201, "close": 205}, {"date": "2023-04-27", "open": 207.7, "high": 207.7, "low": 203.8, "close": 204.75}, {"date": "2023-04-28", "open": 206.05, "high": 210.35, "low": 201.35, "close": 203.95}, {"date": "2023-05-01", "open": 206.05, "high": 210.35, "low": 201.35, "close": 203.95}, {"date": "2023-05-02", "open": 204.1, "high": 212.9, "low": 204, "close": 209}, {"date": "2023-05-03", "open": 209.65, "high": 215.3, "low": 209.65, "close": 213.75}, {"date": "2023-05-04", "open": 214.95, "high": 214.95, "low": 209.65, "close": 211.05}, {"date": "2023-05-05", "open": 211.15, "high": 213.95, "low": 203.75, "close": 205.7}, {"date": "2023-05-08", "open": 206, "high": 207.7, "low": 204, "close": 205.6}, {"date": "2023-05-09", "open": 194.55, "high": 205.6, "low": 194.55, "close": 201.8}, {"date": "2023-05-10", "open": 204.95, "high": 204.95, "low": 200, "close": 203.55}, {"date": "2023-05-11", "open": 207.9, "high": 207.9, "low": 195.5, "close": 197.85}, {"date": "2023-05-12", "open": 201, "high": 204.9, "low": 198, "close": 203.05}, {"date": "2023-05-15", "open": 204.85, "high": 204.85, "low": 198.3, "close": 199.1}, {"date": "2023-05-16", "open": 199.1, "high": 201.85, "low": 196.3, "close": 197.5}, {"date": "2023-05-17", "open": 199.05, "high": 199.95, "low": 197.55, "close": 199}, {"date": "2023-05-18", "open": 199, "high": 207, "low": 197, "close": 202.4}, {"date": "2023-05-19", "open": 202, "high": 202.45, "low": 197.75, "close": 199.05}, {"date": "2023-05-22", "open": 201.3, "high": 201.3, "low": 193.8, "close": 195.95}, {"date": "2023-05-23", "open": 195.05, "high": 199.45, "low": 195.05, "close": 195.75}, {"date": "2023-05-24", "open": 196.15, "high": 199.5, "low": 194, "close": 197.8}, {"date": "2023-05-25", "open": 197.5, "high": 203.25, "low": 196, "close": 199.65}, {"date": "2023-05-26", "open": 200, "high": 204.5, "low": 199, "close": 200.15}, {"date": "2023-05-29", "open": 201, "high": 203.95, "low": 197, "close": 202.2}, {"date": "2023-05-30", "open": 203, "high": 221, "low": 199, "close": 216.4}, {"date": "2023-05-31", "open": 205, "high": 211.95, "low": 196, "close": 200.25}, {"date": "2023-06-01", "open": 200.25, "high": 204, "low": 199, "close": 200.55}, {"date": "2023-06-02", "open": 201.05, "high": 203, "low": 195.55, "close": 197.05}, {"date": "2023-06-05", "open": 200, "high": 201.45, "low": 195.15, "close": 198.4}, {"date": "2023-06-06", "open": 198.4, "high": 207.5, "low": 195.5, "close": 201.6}, {"date": "2023-06-07", "open": 201.8, "high": 204.85, "low": 198.1, "close": 202.25}, {"date": "2023-06-08", "open": 202.4, "high": 202.95, "low": 198.15, "close": 199.4}, {"date": "2023-06-09", "open": 199.9, "high": 200.95, "low": 196.95, "close": 199.25}, {"date": "2023-06-12", "open": 199, "high": 205, "low": 198.05, "close": 202.9}, {"date": "2023-06-13", "open": 200.3, "high": 204.25, "low": 199, "close": 200.3}, {"date": "2023-06-14", "open": 198, "high": 205.4, "low": 198, "close": 203.25}, {"date": "2023-06-15", "open": 205, "high": 212.9, "low": 202.55, "close": 205.65}, {"date": "2023-06-16", "open": 205.7, "high": 218.95, "low": 203.55, "close": 212.15}, {"date": "2023-06-19", "open": 217, "high": 217, "low": 203.65, "close": 206.05}, {"date": "2023-06-20", "open": 204.05, "high": 212.7, "low": 204.05, "close": 209.15}, {"date": "2023-06-21", "open": 212.9, "high": 212.9, "low": 204.85, "close": 209.4}, {"date": "2023-06-22", "open": 210, "high": 211.95, "low": 209.7, "close": 210.7}, {"date": "2023-06-23", "open": 207.1, "high": 212.6, "low": 207.05, "close": 210.05}, {"date": "2023-06-26", "open": 212, "high": 214.45, "low": 207.9, "close": 212.25}, {"date": "2023-06-27", "open": 213, "high": 224, "low": 210.95, "close": 219.8}, {"date": "2023-06-28", "open": 221.8, "high": 225.7, "low": 213, "close": 214.45}, {"date": "2023-06-29", "open": 221.8, "high": 225.7, "low": 213, "close": 214.45}, {"date": "2023-06-30", "open": 214.95, "high": 216, "low": 208, "close": 213.7}, {"date": "2023-07-03", "open": 214.95, "high": 215.85, "low": 208.15, "close": 214.4}, {"date": "2023-07-04", "open": 216, "high": 218.5, "low": 211.05, "close": 216.5}, {"date": "2023-07-05", "open": 213.1, "high": 220, "low": 213.1, "close": 218.1}, {"date": "2023-07-06", "open": 219.3, "high": 229.7, "low": 219.25, "close": 225.1}, {"date": "2023-07-07", "open": 224.9, "high": 254.8, "low": 223.6, "close": 242.6}, {"date": "2023-07-10", "open": 243.8, "high": 250.4, "low": 242.25, "close": 246.4}, {"date": "2023-07-11", "open": 248, "high": 259, "low": 243.65, "close": 256.75}, {"date": "2023-07-12", "open": 257.1, "high": 295, "low": 257.1, "close": 289.1}, {"date": "2023-07-13", "open": 283.1, "high": 285.9, "low": 271.25, "close": 277.65}, {"date": "2023-07-14", "open": 278, "high": 281.4, "low": 265, "close": 267.25}, {"date": "2023-07-17", "open": 267.25, "high": 270.65, "low": 251.5, "close": 255.25}, {"date": "2023-07-18", "open": 255.25, "high": 257.5, "low": 238.4, "close": 241.8}, {"date": "2023-07-19", "open": 241.8, "high": 259.7, "low": 241, "close": 256.55}, {"date": "2023-07-20", "open": 256.8, "high": 267.7, "low": 253, "close": 260.95}, {"date": "2023-07-21", "open": 261.95, "high": 262, "low": 255.25, "close": 258.25}, {"date": "2023-07-24", "open": 260.25, "high": 260.25, "low": 246.55, "close": 250.25}, {"date": "2023-07-25", "open": 250, "high": 252.3, "low": 245.55, "close": 246.5}, {"date": "2023-07-26", "open": 246.5, "high": 259.2, "low": 246.5, "close": 257}, {"date": "2023-07-27", "open": 257, "high": 257, "low": 249.5, "close": 249.7}, {"date": "2023-07-28", "open": 251.9, "high": 252.75, "low": 240.5, "close": 245.9}, {"date": "2023-07-31", "open": 249.6, "high": 252.2, "low": 240.5, "close": 241.55}, {"date": "2023-08-01", "open": 243.5, "high": 246, "low": 240, "close": 244.7}, {"date": "2023-08-02", "open": 244.6, "high": 244.65, "low": 236.25, "close": 237.45}, {"date": "2023-08-03", "open": 236, "high": 242, "low": 236, "close": 240.35}, {"date": "2023-08-04", "open": 244, "high": 244.8, "low": 238.3, "close": 243.35}, {"date": "2023-08-07", "open": 244.9, "high": 244.95, "low": 236.35, "close": 239.4}, {"date": "2023-08-08", "open": 239.45, "high": 259.4, "low": 238, "close": 255.05}, {"date": "2023-08-09", "open": 256.35, "high": 261.95, "low": 250, "close": 252.05}, {"date": "2023-08-11", "open": 250, "high": 254.95, "low": 248.5, "close": 250.5}, {"date": "2023-08-14", "open": 250.6, "high": 254.95, "low": 243, "close": 250.25}, {"date": "2023-08-15", "open": 250.6, "high": 254.95, "low": 243, "close": 250.25}, {"date": "2023-08-16", "open": 250.25, "high": 250.25, "low": 242, "close": 244.5}, {"date": "2023-08-17", "open": 244.5, "high": 247.5, "low": 237.65, "close": 238.85}, {"date": "2023-08-18", "open": 241.3, "high": 257, "low": 238.15, "close": 254.05}, {"date": "2023-08-21", "open": 256.75, "high": 293.4, "low": 254.55, "close": 280.35}, {"date": "2023-08-22", "open": 284, "high": 308.4, "low": 282, "close": 293.9}, {"date": "2023-08-23", "open": 295.35, "high": 308.6, "low": 294, "close": 297.55}, {"date": "2023-08-24", "open": 295.5, "high": 299.75, "low": 279.6, "close": 284.3}, {"date": "2023-08-25", "open": 283.7, "high": 290, "low": 276.95, "close": 284.95}, {"date": "2023-08-28", "open": 285.4, "high": 288.1, "low": 277.1, "close": 280.25}, {"date": "2023-08-29", "open": 282.1, "high": 289.5, "low": 278.2, "close": 287.75}, {"date": "2023-08-30", "open": 287.75, "high": 287.75, "low": 278.05, "close": 280.6}, {"date": "2023-08-31", "open": 280.8, "high": 283.6, "low": 272.05, "close": 272.7}, {"date": "2023-09-01", "open": 275.3, "high": 282.45, "low": 271, "close": 278.25}, {"date": "2023-09-04", "open": 280.3, "high": 282.9, "low": 268, "close": 272.55}, {"date": "2023-09-05", "open": 279.7, "high": 279.7, "low": 272.65, "close": 275.65}, {"date": "2023-09-06", "open": 274.75, "high": 276.25, "low": 271.15, "close": 275.3}, {"date": "2023-09-07", "open": 276.95, "high": 287.5, "low": 275.8, "close": 281.45}, {"date": "2023-09-08", "open": 283.8, "high": 290, "low": 273.95, "close": 285}, {"date": "2023-09-11", "open": 285.5, "high": 286.9, "low": 269.8, "close": 274.45}, {"date": "2023-09-12", "open": 278.5, "high": 278.5, "low": 256.25, "close": 259.95}, {"date": "2023-09-13", "open": 259, "high": 263.65, "low": 252.25, "close": 260.35}, {"date": "2023-09-14", "open": 259.8, "high": 284.3, "low": 259.8, "close": 271.3}, {"date": "2023-09-15", "open": 272.7, "high": 276.7, "low": 264.3, "close": 268}, {"date": "2023-09-18", "open": 271, "high": 273, "low": 258, "close": 259.8}, {"date": "2023-09-19", "open": 271, "high": 273, "low": 258, "close": 259.8}, {"date": "2023-09-20", "open": 255.35, "high": 268.95, "low": 254.65, "close": 264.65}, {"date": "2023-09-21", "open": 266.9, "high": 271.9, "low": 251.9, "close": 255.4}, {"date": "2023-09-22", "open": 260, "high": 286.9, "low": 255.35, "close": 264.05}, {"date": "2023-09-25", "open": 264.5, "high": 273.55, "low": 260.4, "close": 265.75}, {"date": "2023-09-26", "open": 265.1, "high": 265.8, "low": 260.1, "close": 262.3}, {"date": "2023-09-27", "open": 276.95, "high": 276.95, "low": 260.15, "close": 262.9}, {"date": "2023-09-28", "open": 263.65, "high": 265, "low": 259.1, "close": 260.95}, {"date": "2023-09-29", "open": 258.05, "high": 264, "low": 256.35, "close": 261.75}, {"date": "2023-10-02", "open": 258.05, "high": 264, "low": 256.35, "close": 261.75}, {"date": "2023-10-03", "open": 258.9, "high": 263.8, "low": 257.4, "close": 261.95}, {"date": "2023-10-04", "open": 257.1, "high": 263.25, "low": 253.1, "close": 258}, {"date": "2023-10-05", "open": 257.1, "high": 260.1, "low": 252.55, "close": 253.85}, {"date": "2023-10-06", "open": 252.15, "high": 262, "low": 251.8, "close": 259.2}, {"date": "2023-10-09", "open": 257, "high": 257.15, "low": 249.2, "close": 252.9}, {"date": "2023-10-10", "open": 251.9, "high": 255, "low": 246.65, "close": 248.65}, {"date": "2023-10-11", "open": 253.5, "high": 267, "low": 248.75, "close": 266.25}, {"date": "2023-10-12", "open": 267, "high": 272.3, "low": 259, "close": 263.7}, {"date": "2023-10-13", "open": 258, "high": 263.4, "low": 257.95, "close": 259.85}, {"date": "2023-10-16", "open": 259.75, "high": 279.65, "low": 257, "close": 265.4}, {"date": "2023-10-17", "open": 265.65, "high": 270, "low": 262, "close": 264.85}, {"date": "2023-10-18", "open": 269.95, "high": 279, "low": 265.5, "close": 271.3}, {"date": "2023-10-19", "open": 265, "high": 279, "low": 263.9, "close": 271.35}, {"date": "2023-10-20", "open": 271.75, "high": 272.9, "low": 263, "close": 267.7}, {"date": "2023-10-23", "open": 267, "high": 272.1, "low": 232.85, "close": 250.1}, {"date": "2023-10-24", "open": 267, "high": 272.1, "low": 232.85, "close": 250.1}, {"date": "2023-10-25", "open": 250, "high": 253.9, "low": 236, "close": 238.3}, {"date": "2023-10-26", "open": 240, "high": 250.6, "low": 232.55, "close": 247.75}, {"date": "2023-10-27", "open": 248.7, "high": 253.6, "low": 247, "close": 249.95}, {"date": "2023-10-30", "open": 245, "high": 254, "low": 243.1, "close": 245.9}, {"date": "2023-10-31", "open": 249.2, "high": 249.2, "low": 240.4, "close": 242.95}, {"date": "2023-11-01", "open": 244.1, "high": 247.4, "low": 243, "close": 245.05}, {"date": "2023-11-02", "open": 246.85, "high": 248.65, "low": 241.05, "close": 245.2}, {"date": "2023-11-03", "open": 246.9, "high": 248.9, "low": 244.9, "close": 247.85}, {"date": "2023-11-06", "open": 253.25, "high": 259.95, "low": 250.45, "close": 257.05}, {"date": "2023-11-07", "open": 251.35, "high": 261.1, "low": 251.35, "close": 258.95}, {"date": "2023-11-08", "open": 259.4, "high": 263.45, "low": 254.2, "close": 257.35}, {"date": "2023-11-09", "open": 261.35, "high": 264, "low": 253.05, "close": 256.4}, {"date": "2023-11-10", "open": 254.85, "high": 256.85, "low": 252.3, "close": 253.7}, {"date": "2023-11-13", "open": 257.5, "high": 272.35, "low": 252.3, "close": 267.5}, {"date": "2023-11-14", "open": 257.5, "high": 272.35, "low": 252.3, "close": 267.5}, {"date": "2023-11-15", "open": 267.5, "high": 267.5, "low": 243.05, "close": 248.85}, {"date": "2023-11-16", "open": 254.25, "high": 254.25, "low": 248.55, "close": 250.1}, {"date": "2023-11-17", "open": 254.65, "high": 254.65, "low": 250, "close": 251.5}, {"date": "2023-11-20", "open": 251.95, "high": 258.85, "low": 248.55, "close": 253.9}, {"date": "2023-11-21", "open": 253.9, "high": 255.85, "low": 250, "close": 251.15}, {"date": "2023-11-22", "open": 251.15, "high": 255, "low": 238.75, "close": 245.05}, {"date": "2023-11-23", "open": 248.75, "high": 249.85, "low": 243, "close": 244.3}, {"date": "2023-11-24", "open": 247.85, "high": 247.85, "low": 243.8, "close": 245.55}, {"date": "2023-11-27", "open": 247.85, "high": 247.85, "low": 243.8, "close": 245.55}, {"date": "2023-11-28", "open": 248.6, "high": 253.95, "low": 246, "close": 247.55}, {"date": "2023-11-29", "open": 248.8, "high": 256, "low": 248.8, "close": 253.7}, {"date": "2023-11-30", "open": 253.7, "high": 254, "low": 249, "close": 251}, {"date": "2023-12-01", "open": 252.1, "high": 254.6, "low": 248.4, "close": 249.75}, {"date": "2023-12-04", "open": 251.1, "high": 253.25, "low": 245.55, "close": 247.95}, {"date": "2023-12-05", "open": 249, "high": 252.75, "low": 247.3, "close": 250.55}, {"date": "2023-12-06", "open": 251.85, "high": 253.15, "low": 249.3, "close": 251.55}, {"date": "2023-12-07", "open": 252, "high": 262.8, "low": 252, "close": 257.1}, {"date": "2023-12-08", "open": 258.95, "high": 263.65, "low": 252.6, "close": 255.7}, {"date": "2023-12-11", "open": 255.7, "high": 271.75, "low": 255.7, "close": 266.7}, {"date": "2023-12-12", "open": 269.9, "high": 272.9, "low": 267.1, "close": 269.2}, {"date": "2023-12-13", "open": 265, "high": 276.45, "low": 265, "close": 272.65}, {"date": "2023-12-14", "open": 275.95, "high": 275.95, "low": 266.65, "close": 268}, {"date": "2023-12-15", "open": 263, "high": 281.5, "low": 263, "close": 276.55}, {"date": "2023-12-18", "open": 277.6, "high": 279.45, "low": 271.3, "close": 274.65}, {"date": "2023-12-19", "open": 278.95, "high": 282, "low": 271.05, "close": 278.55}, {"date": "2023-12-20", "open": 278.55, "high": 282.95, "low": 257.6, "close": 260.1}, {"date": "2023-12-21", "open": 260.1, "high": 268.4, "low": 259, "close": 263.75}, {"date": "2023-12-22", "open": 267.95, "high": 269, "low": 261.55, "close": 263.65}, {"date": "2023-12-25", "open": 267.95, "high": 269, "low": 261.55, "close": 263.65}, {"date": "2023-12-26", "open": 266, "high": 269.9, "low": 262.1, "close": 267.95}, {"date": "2023-12-27", "open": 265.6, "high": 272.95, "low": 263.65, "close": 264.7}, {"date": "2023-12-28", "open": 264.7, "high": 269, "low": 258, "close": 259.35}, {"date": "2023-12-29", "open": 260.75, "high": 264, "low": 258, "close": 261.15}, {"date": "2024-01-01", "open": 261.15, "high": 287, "low": 261.15, "close": 281.8}, {"date": "2024-01-02", "open": 284.65, "high": 290.65, "low": 275.4, "close": 281.9}, {"date": "2024-01-03", "open": 277.4, "high": 297, "low": 275.55, "close": 293.7}, {"date": "2024-01-04", "open": 299, "high": 329.4, "low": 293.15, "close": 320}, {"date": "2024-01-05", "open": 321.6, "high": 337.75, "low": 304.65, "close": 314.05}, {"date": "2024-01-08", "open": 327, "high": 334.45, "low": 317.15, "close": 326.7}, {"date": "2024-01-09", "open": 329, "high": 331.6, "low": 313.8, "close": 315.7}, {"date": "2024-01-10", "open": 319.85, "high": 330.8, "low": 317.8, "close": 325.4}, {"date": "2024-01-11", "open": 328.05, "high": 334.8, "low": 321.25, "close": 331.05}, {"date": "2024-01-12", "open": 333.85, "high": 354.15, "low": 326.85, "close": 335.35}, {"date": "2024-01-15", "open": 337.9, "high": 345, "low": 328.8, "close": 331.5}, {"date": "2024-01-16", "open": 330.95, "high": 331.95, "low": 315.6, "close": 321.7}, {"date": "2024-01-17", "open": 318.6, "high": 330.85, "low": 316.35, "close": 318.9}, {"date": "2024-01-18", "open": 318.9, "high": 322, "low": 305, "close": 312.35}, {"date": "2024-01-19", "open": 314.2, "high": 326.2, "low": 313.6, "close": 320.35}, {"date": "2024-01-22", "open": 320, "high": 322.8, "low": 309.5, "close": 313.2}, {"date": "2024-01-23", "open": 303.55, "high": 315.7, "low": 292.75, "close": 303.3}, {"date": "2024-01-24", "open": 297.15, "high": 306.4, "low": 294, "close": 296.95}, {"date": "2024-01-25", "open": 297, "high": 304.45, "low": 297, "close": 299.05}, {"date": "2024-01-26", "open": 297, "high": 304.45, "low": 297, "close": 299.05}, {"date": "2024-01-29", "open": 294, "high": 316.55, "low": 294, "close": 297.5}, {"date": "2024-01-30", "open": 297.5, "high": 305, "low": 296.25, "close": 297.9}, {"date": "2024-01-31", "open": 303.85, "high": 312.7, "low": 297, "close": 303.05}, {"date": "2024-02-01", "open": 307.9, "high": 328.2, "low": 304.45, "close": 318.6}, {"date": "2024-02-02", "open": 328.8, "high": 328.8, "low": 316, "close": 319.4}, {"date": "2024-02-05", "open": 322, "high": 322.5, "low": 305.55, "close": 311.55}, {"date": "2024-02-06", "open": 311.55, "high": 314.45, "low": 301.35, "close": 308.3}, {"date": "2024-02-07", "open": 310.25, "high": 313.45, "low": 302.2, "close": 306.4}, {"date": "2024-02-08", "open": 301, "high": 311, "low": 292.8, "close": 302.95}, {"date": "2024-02-09", "open": 313, "high": 313, "low": 293, "close": 295.95}, {"date": "2024-02-12", "open": 286.05, "high": 303.85, "low": 281.8, "close": 284.15}, {"date": "2024-02-13", "open": 298.8, "high": 298.8, "low": 264.05, "close": 276.1}, {"date": "2024-02-14", "open": 271, "high": 281, "low": 271, "close": 275.7}, {"date": "2024-02-15", "open": 279.9, "high": 295, "low": 278.6, "close": 291.9}, {"date": "2024-02-16", "open": 297.95, "high": 297.95, "low": 288.6, "close": 290.75}, {"date": "2024-02-19", "open": 292, "high": 309.45, "low": 292, "close": 300.95}, {"date": "2024-02-20", "open": 304.05, "high": 305.7, "low": 293.05, "close": 294.2}, {"date": "2024-02-21", "open": 299.4, "high": 304.4, "low": 294.4, "close": 296.85}, {"date": "2024-02-22", "open": 297.15, "high": 300, "low": 292.3, "close": 294.95}, {"date": "2024-02-23", "open": 296.45, "high": 304, "low": 292.3, "close": 293.5}, {"date": "2024-02-26", "open": 299, "high": 299, "low": 287.3, "close": 294.65}, {"date": "2024-02-27", "open": 298, "high": 298, "low": 288, "close": 289.5}, {"date": "2024-02-28", "open": 290, "high": 294.3, "low": 285, "close": 286.15}, {"date": "2024-02-29", "open": 288.55, "high": 290, "low": 280.15, "close": 282.05}, {"date": "2024-03-01", "open": 289.8, "high": 294.9, "low": 285, "close": 286.1}, {"date": "2024-03-04", "open": 297.85, "high": 302.7, "low": 288.05, "close": 293.25}, {"date": "2024-03-05", "open": 290.1, "high": 298.7, "low": 286, "close": 288.1}, {"date": "2024-03-06", "open": 292.9, "high": 292.9, "low": 271.6, "close": 278.35}, {"date": "2024-03-07", "open": 278.45, "high": 288.4, "low": 275.6, "close": 284.3}, {"date": "2024-03-08", "open": 278.45, "high": 288.4, "low": 275.6, "close": 284.3}, {"date": "2024-03-11", "open": 278.5, "high": 283.95, "low": 265, "close": 270.9}, {"date": "2024-03-12", "open": 270.9, "high": 270.9, "low": 257.05, "close": 258.4}, {"date": "2024-03-13", "open": 260, "high": 262.95, "low": 233, "close": 243.55}, {"date": "2024-03-14", "open": 246.95, "high": 257.95, "low": 235.3, "close": 246.55}, {"date": "2024-03-15", "open": 245, "high": 249.5, "low": 234.95, "close": 239.7}, {"date": "2024-03-18", "open": 243.95, "high": 248.9, "low": 232.1, "close": 242.7}, {"date": "2024-03-19", "open": 240.7, "high": 248.5, "low": 239.5, "close": 245.65}, {"date": "2024-03-20", "open": 240.45, "high": 247.45, "low": 238.05, "close": 243.3}, {"date": "2024-03-21", "open": 247.65, "high": 253.65, "low": 241.5, "close": 249.3}, {"date": "2024-03-22", "open": 249.95, "high": 255, "low": 247, "close": 249.2}, {"date": "2024-03-25", "open": 249.95, "high": 255, "low": 247, "close": 249.2}, {"date": "2024-03-26", "open": 248.95, "high": 253.1, "low": 242.75, "close": 246.2}, {"date": "2024-03-27", "open": 245, "high": 247.3, "low": 238.6, "close": 240.5}, {"date": "2024-03-28", "open": 237, "high": 248.7, "low": 237, "close": 237.95}, {"date": "2024-03-29", "open": 237, "high": 248.7, "low": 237, "close": 237.95}, {"date": "2024-04-01", "open": 246.8, "high": 250.7, "low": 241.55, "close": 248.9}, {"date": "2024-04-02", "open": 251.65, "high": 256.8, "low": 247.1, "close": 251.1}, {"date": "2024-04-03", "open": 252.7, "high": 253.95, "low": 242.8, "close": 244.7}, {"date": "2024-04-04", "open": 245.2, "high": 251.8, "low": 241.6, "close": 244.25}, {"date": "2024-04-05", "open": 248.95, "high": 259.8, "low": 247.7, "close": 256.75}, {"date": "2024-04-08", "open": 258.6, "high": 263.45, "low": 250.2, "close": 257.65}, {"date": "2024-04-09", "open": 259.85, "high": 260.95, "low": 251.95, "close": 254}, {"date": "2024-04-10", "open": 253.85, "high": 259, "low": 252.3, "close": 254.8}, {"date": "2024-04-11", "open": 253.85, "high": 259, "low": 252.3, "close": 254.8}, {"date": "2024-04-12", "open": 253.05, "high": 257, "low": 248.05, "close": 250.55}, {"date": "2024-04-15", "open": 245, "high": 252.55, "low": 240.55, "close": 249.5}, {"date": "2024-04-16", "open": 247.5, "high": 257.35, "low": 242.5, "close": 256.35}, {"date": "2024-04-17", "open": 247.5, "high": 257.35, "low": 242.5, "close": 256.35}, {"date": "2024-04-18", "open": 268.3, "high": 268.3, "low": 251.6, "close": 253.5}, {"date": "2024-04-19", "open": 245.1, "high": 257, "low": 245.1, "close": 251.8}, {"date": "2024-04-22", "open": 254.05, "high": 254.7, "low": 240.25, "close": 246.25}, {"date": "2024-04-23", "open": 248.15, "high": 259, "low": 247.5, "close": 252.4}, {"date": "2024-04-24", "open": 252.55, "high": 255.4, "low": 250, "close": 250.65}, {"date": "2024-04-25", "open": 253.9, "high": 262.15, "low": 251, "close": 258.15}, {"date": "2024-04-26", "open": 255.5, "high": 260.45, "low": 252.6, "close": 258.25}, {"date": "2024-04-29", "open": 258.3, "high": 260.8, "low": 252.05, "close": 253.45}, {"date": "2024-04-30", "open": 254.15, "high": 258.55, "low": 250, "close": 251.4}, {"date": "2024-05-01", "open": 254.15, "high": 258.55, "low": 250, "close": 251.4}, {"date": "2024-05-02", "open": 254, "high": 259, "low": 249.4, "close": 253.55}, {"date": "2024-05-03", "open": 252.8, "high": 257.9, "low": 252.05, "close": 254.45}, {"date": "2024-05-06", "open": 252.6, "high": 253.15, "low": 241, "close": 243.05}, {"date": "2024-05-07", "open": 244.6, "high": 244.7, "low": 239, "close": 241.95}, {"date": "2024-05-08", "open": 245.3, "high": 246, "low": 240.2, "close": 244.35}, {"date": "2024-05-09", "open": 246.8, "high": 246.8, "low": 235.25, "close": 237.05}, {"date": "2024-05-10", "open": 241.75, "high": 241.75, "low": 236.3, "close": 240}, {"date": "2024-05-13", "open": 243.6, "high": 243.6, "low": 235.6, "close": 241.7}, {"date": "2024-05-14", "open": 241.95, "high": 245, "low": 239.05, "close": 240.4}, {"date": "2024-05-15", "open": 237.4, "high": 247.25, "low": 237.4, "close": 242.5}, {"date": "2024-05-16", "open": 241.9, "high": 243.95, "low": 240.4, "close": 241.9}, {"date": "2024-05-17", "open": 242.3, "high": 249.05, "low": 240.55, "close": 246.35}, {"date": "2024-05-20", "open": 253, "high": 253, "low": 243.1, "close": 244.75}, {"date": "2024-05-21", "open": 244.75, "high": 249.35, "low": 230.5, "close": 236.95}, {"date": "2024-05-22", "open": 239.9, "high": 240, "low": 232.8, "close": 236.55}, {"date": "2024-05-23", "open": 238.05, "high": 242.45, "low": 233.2, "close": 240.3}, {"date": "2024-05-24", "open": 237.05, "high": 242.9, "low": 236.3, "close": 239}, {"date": "2024-05-27", "open": 245, "high": 245.15, "low": 235.2, "close": 238.05}, {"date": "2024-05-28", "open": 230, "high": 235.2, "low": 218.35, "close": 225.15}, {"date": "2024-05-29", "open": 223.45, "high": 225, "low": 218.85, "close": 223.25}, {"date": "2024-05-30", "open": 227.65, "high": 227.65, "low": 218, "close": 219.75}, {"date": "2024-05-31", "open": 224.05, "high": 228.8, "low": 220.45, "close": 224.15}, {"date": "2024-06-03", "open": 230, "high": 230, "low": 223.05, "close": 224.75}, {"date": "2024-06-04", "open": 226.55, "high": 226.55, "low": 208.5, "close": 216.6}, {"date": "2024-06-05", "open": 216.6, "high": 220, "low": 213.35, "close": 219.45}, {"date": "2024-06-06", "open": 223.75, "high": 224.9, "low": 218.4, "close": 219.55}, {"date": "2024-06-07", "open": 221.6, "high": 231.4, "low": 221, "close": 225.75}, {"date": "2024-06-10", "open": 229.9, "high": 247, "low": 228.2, "close": 241.34}, {"date": "2024-06-11", "open": 243, "high": 249.25, "low": 233.45, "close": 234.4}, {"date": "2024-06-12", "open": 239, "high": 239.76, "low": 232.05, "close": 233.85}, {"date": "2024-06-13", "open": 238, "high": 238, "low": 230.8, "close": 232.72}, {"date": "2024-06-14", "open": 235.5, "high": 235.5, "low": 225.37, "close": 227.58}, {"date": "2024-06-17", "open": 235.5, "high": 235.5, "low": 225.37, "close": 227.58}, {"date": "2024-06-18", "open": 228, "high": 229.78, "low": 225.95, "close": 226.7}, {"date": "2024-06-19", "open": 228.14, "high": 239.4, "low": 224.99, "close": 234.84}, {"date": "2024-06-20", "open": 237.2, "high": 241, "low": 231.8, "close": 235.08}, {"date": "2024-06-21", "open": 237.1, "high": 237.39, "low": 226.5, "close": 229.81}, {"date": "2024-06-24", "open": 228.1, "high": 234.35, "low": 228, "close": 229.8}, {"date": "2024-06-25", "open": 230.86, "high": 231.8, "low": 228, "close": 228.56}, {"date": "2024-06-26", "open": 230.84, "high": 230.84, "low": 226, "close": 227.34}, {"date": "2024-06-27", "open": 230.75, "high": 230.75, "low": 226, "close": 228.2}, {"date": "2024-06-28", "open": 229, "high": 230, "low": 226.65, "close": 226.96}, {"date": "2024-07-01", "open": 230.8, "high": 230.8, "low": 227.4, "close": 228.83}, {"date": "2024-07-02", "open": 229, "high": 233, "low": 226.17, "close": 227.08}, {"date": "2024-07-03", "open": 228.38, "high": 233, "low": 227, "close": 227.52}, {"date": "2024-07-04", "open": 228.63, "high": 242, "low": 228.1, "close": 240.27}, {"date": "2024-07-05", "open": 242, "high": 255.59, "low": 237.41, "close": 253.02}, {"date": "2024-07-08", "open": 257.45, "high": 268.9, "low": 248.21, "close": 264.54}, {"date": "2024-07-09", "open": 265, "high": 277, "low": 256.2, "close": 260.41}, {"date": "2024-07-10", "open": 258, "high": 259.85, "low": 247, "close": 251.33}, {"date": "2024-07-11", "open": 251.25, "high": 263.19, "low": 251.25, "close": 252.25}, {"date": "2024-07-12", "open": 256.31, "high": 258.39, "low": 242.9, "close": 245.89}, {"date": "2024-07-15", "open": 247.16, "high": 247.21, "low": 241, "close": 244.78}, {"date": "2024-07-16", "open": 246.8, "high": 253.59, "low": 245.01, "close": 246.48}, {"date": "2024-07-17", "open": 246.8, "high": 253.59, "low": 245.01, "close": 246.48}, {"date": "2024-07-18", "open": 262.99, "high": 294.85, "low": 255.2, "close": 274.77}, {"date": "2024-07-19", "open": 273.86, "high": 282.45, "low": 265, "close": 269.12}, {"date": "2024-07-22", "open": 270, "high": 283, "low": 263.13, "close": 276.18}, {"date": "2024-07-23", "open": 280, "high": 298.99, "low": 263.9, "close": 281.97}, {"date": "2024-07-24", "open": 293.44, "high": 321, "low": 287.7, "close": 308.04}, {"date": "2024-07-25", "open": 309.31, "high": 323.18, "low": 302.7, "close": 307.15}, {"date": "2024-07-26", "open": 307.15, "high": 324.19, "low": 300.2, "close": 302.65}, {"date": "2024-07-29", "open": 303, "high": 305.14, "low": 293.7, "close": 297.12}, {"date": "2024-07-30", "open": 299, "high": 306.79, "low": 297.92, "close": 303.08}, {"date": "2024-07-31", "open": 305.4, "high": 307.45, "low": 302.5, "close": 303.25}, {"date": "2024-08-01", "open": 303.25, "high": 312, "low": 300, "close": 307.55}, {"date": "2024-08-02", "open": 303.55, "high": 310.7, "low": 300.5, "close": 304.6}, {"date": "2024-08-05", "open": 299.75, "high": 299.75, "low": 281, "close": 285.75}, {"date": "2024-08-06", "open": 285.75, "high": 292.45, "low": 279, "close": 281.2}, {"date": "2024-08-07", "open": 282.8, "high": 304, "low": 280.7, "close": 298.1}, {"date": "2024-08-08", "open": 298.1, "high": 301.8, "low": 287, "close": 290.45}, {"date": "2024-08-09", "open": 291.8, "high": 314, "low": 291.8, "close": 307.3}, {"date": "2024-08-12", "open": 304.5, "high": 310.75, "low": 298, "close": 300.1}, {"date": "2024-08-13", "open": 300, "high": 313.2, "low": 290.6, "close": 297.6}, {"date": "2024-08-14", "open": 298.55, "high": 309, "low": 263.35, "close": 270.2}, {"date": "2024-08-15", "open": 298.55, "high": 309, "low": 263.35, "close": 270.2}, {"date": "2024-08-16", "open": 270.2, "high": 277.75, "low": 266.2, "close": 271.45}, {"date": "2024-08-19", "open": 274.9, "high": 276.5, "low": 265.05, "close": 266}, {"date": "2024-08-20", "open": 271.75, "high": 272, "low": 265.8, "close": 267.45}, {"date": "2024-08-21", "open": 265, "high": 290, "low": 265, "close": 283.35}, {"date": "2024-08-22", "open": 283.45, "high": 300, "low": 278, "close": 293.35}, {"date": "2024-08-23", "open": 293.95, "high": 295.95, "low": 283.15, "close": 289.65}, {"date": "2024-08-26", "open": 293, "high": 298.9, "low": 281.1, "close": 286.45}, {"date": "2024-08-27", "open": 281.7, "high": 289.85, "low": 281.7, "close": 282.85}, {"date": "2024-08-28", "open": 287, "high": 290, "low": 277.85, "close": 280.75}, {"date": "2024-08-29", "open": 280.75, "high": 287, "low": 271.25, "close": 272.75}, {"date": "2024-08-30", "open": 279.45, "high": 279.45, "low": 270.5, "close": 272.1}, {"date": "2024-09-02", "open": 268.55, "high": 276.9, "low": 267.05, "close": 270.75}, {"date": "2024-09-03", "open": 272, "high": 274.1, "low": 265.9, "close": 268}, {"date": "2024-09-04", "open": 268, "high": 274.8, "low": 265.25, "close": 272.85}, {"date": "2024-09-05", "open": 275.15, "high": 276.85, "low": 271.95, "close": 275.4}, {"date": "2024-09-06", "open": 278.6, "high": 279.25, "low": 272.1, "close": 273.75}, {"date": "2024-09-10", "open": 273.65, "high": 274.2, "low": 267.05, "close": 268.7}, {"date": "2024-09-11", "open": 266.15, "high": 272.9, "low": 264.05, "close": 265.15}, {"date": "2024-09-12", "open": 265, "high": 270.5, "low": 261, "close": 261.8}, {"date": "2024-09-13", "open": 262.95, "high": 279.75, "low": 262.05, "close": 272.15}, {"date": "2024-09-16", "open": 272.8, "high": 273.95, "low": 267.3, "close": 269.55}, {"date": "2024-09-17", "open": 271.55, "high": 275.15, "low": 266.25, "close": 270.4}, {"date": "2024-09-18", "open": 270.35, "high": 270.35, "low": 263.3, "close": 267.4}, {"date": "2024-09-19", "open": 270.65, "high": 270.75, "low": 256.05, "close": 259.6}, {"date": "2024-09-20", "open": 259.6, "high": 264.25, "low": 256.95, "close": 258.65}, {"date": "2024-09-23", "open": 256.55, "high": 264, "low": 254, "close": 256.05}, {"date": "2024-09-24", "open": 263.6, "high": 263.6, "low": 254.5, "close": 255.15}, {"date": "2024-09-25", "open": 253, "high": 261.45, "low": 252.3, "close": 258.1}, {"date": "2024-09-26", "open": 258.1, "high": 261.85, "low": 250.85, "close": 252.5}, {"date": "2024-09-27", "open": 253.5, "high": 255.55, "low": 245.4, "close": 249.5}, {"date": "2024-09-30", "open": 251, "high": 254.95, "low": 241, "close": 247.3}, {"date": "2024-10-01", "open": 253.8, "high": 253.8, "low": 245.1, "close": 246.34}, {"date": "2024-10-02", "open": 253.8, "high": 253.8, "low": 245.1, "close": 246.34}, {"date": "2024-10-03", "open": 249.35, "high": 249.35, "low": 241, "close": 243.11}, {"date": "2024-10-04", "open": 241.5, "high": 246.96, "low": 234.91, "close": 240.43}, {"date": "2024-10-07", "open": 249.9, "high": 254.95, "low": 231.75, "close": 252.05}, {"date": "2024-10-08", "open": 252, "high": 263, "low": 247.85, "close": 248.75}, {"date": "2024-10-09", "open": 249, "high": 253.59, "low": 242.35, "close": 243.94}, {"date": "2024-10-10", "open": 248.75, "high": 259, "low": 247.49, "close": 257.02}, {"date": "2024-10-11", "open": 261, "high": 262, "low": 251.45, "close": 254.02}, {"date": "2024-10-14", "open": 260, "high": 262, "low": 256.65, "close": 260.42}, {"date": "2024-10-15", "open": 261.58, "high": 273.96, "low": 260.91, "close": 269.93}, {"date": "2024-10-16", "open": 273.8, "high": 277.5, "low": 270.02, "close": 275.12}, {"date": "2024-10-17", "open": 276.64, "high": 277.55, "low": 267.5, "close": 269.48}, {"date": "2024-10-18", "open": 266.39, "high": 273.74, "low": 262, "close": 267.23}, {"date": "2024-10-21", "open": 270, "high": 270, "low": 256, "close": 257.47}, {"date": "2024-10-22", "open": 257.47, "high": 260.21, "low": 239.95, "close": 241.14}, {"date": "2024-10-23", "open": 241, "high": 248, "low": 237.97, "close": 239.29}, {"date": "2024-10-24", "open": 240.9, "high": 250.99, "low": 239.1, "close": 246.07}, {"date": "2024-10-25", "open": 244, "high": 264, "low": 240, "close": 241.45}, {"date": "2024-10-28", "open": 237.01, "high": 250.89, "low": 237.01, "close": 241.74}, {"date": "2024-10-29", "open": 252, "high": 258.49, "low": 246.7, "close": 253.4}, {"date": "2024-10-30", "open": 257.9, "high": 258.6, "low": 243.91, "close": 244.35}, {"date": "2024-10-31", "open": 249.73, "high": 253.87, "low": 242.01, "close": 245.45}, {"date": "2024-11-01", "open": 250.4, "high": 253.99, "low": 245.98, "close": 247.56}, {"date": "2024-11-04", "open": 252.44, "high": 252.44, "low": 242, "close": 243.6}, {"date": "2024-11-05", "open": 243.83, "high": 246, "low": 240.5, "close": 241.58}, {"date": "2024-11-06", "open": 240, "high": 260, "low": 240, "close": 257.29}, {"date": "2024-11-07", "open": 262.35, "high": 272.7, "low": 252.5, "close": 264.33}, {"date": "2024-11-08", "open": 264.33, "high": 273.85, "low": 262.45, "close": 272.88}, {"date": "2024-11-11", "open": 275, "high": 282.95, "low": 270, "close": 275.49}, {"date": "2024-11-12", "open": 272.55, "high": 282, "low": 233.86, "close": 237.98}, {"date": "2024-11-13", "open": 226, "high": 238.48, "low": 225.32, "close": 229.41}, {"date": "2024-11-14", "open": 231.94, "high": 232, "low": 222.15, "close": 225.48}, {"date": "2024-11-18", "open": 228.85, "high": 232.4, "low": 217.85, "close": 221.03}, {"date": "2024-11-19", "open": 221.9, "high": 233.62, "low": 221, "close": 227.84}, {"date": "2024-11-20", "open": 221.9, "high": 233.62, "low": 221, "close": 227.84}, {"date": "2024-11-21", "open": 232.34, "high": 237.07, "low": 226.95, "close": 234.55}, {"date": "2024-11-22", "open": 236.02, "high": 245.1, "low": 230.82, "close": 240.14}, {"date": "2024-11-25", "open": 241, "high": 246.75, "low": 235.5, "close": 238.36}, {"date": "2024-11-26", "open": 244.99, "high": 244.99, "low": 236.11, "close": 240}, {"date": "2024-11-27", "open": 240.63, "high": 240.63, "low": 234.33, "close": 236.79}, {"date": "2024-11-28", "open": 240, "high": 243, "low": 237.36, "close": 239.91}, {"date": "2024-11-29", "open": 240.51, "high": 242.84, "low": 238.51, "close": 239.87}, {"date": "2024-12-02", "open": 242.15, "high": 242.15, "low": 236.01, "close": 238.07}, {"date": "2024-12-03", "open": 239.85, "high": 244.5, "low": 235.99, "close": 242.13}, {"date": "2024-12-04", "open": 244.84, "high": 246.4, "low": 239.22, "close": 240.38}, {"date": "2024-12-05", "open": 241.8, "high": 248.67, "low": 238.1, "close": 240.31}, {"date": "2024-12-06", "open": 239, "high": 247, "low": 239, "close": 241.75}, {"date": "2024-12-09", "open": 244, "high": 255.16, "low": 242.86, "close": 246.18}, {"date": "2024-12-10", "open": 250, "high": 264.1, "low": 247, "close": 260.21}, {"date": "2024-12-11", "open": 261.97, "high": 264.65, "low": 251.25, "close": 253.21}, {"date": "2024-12-12", "open": 257, "high": 263.01, "low": 253.33, "close": 258.53}, {"date": "2024-12-13", "open": 256.21, "high": 262, "low": 251.05, "close": 256.67}, {"date": "2024-12-16", "open": 258.99, "high": 268.7, "low": 255, "close": 261.72}, {"date": "2024-12-17", "open": 262.65, "high": 266, "low": 255.4, "close": 260.1}, {"date": "2024-12-18", "open": 264.38, "high": 264.38, "low": 250.82, "close": 251.25}, {"date": "2024-12-19", "open": 255, "high": 276.67, "low": 255, "close": 269.47}, {"date": "2024-12-20", "open": 267.5, "high": 269.39, "low": 255.05, "close": 256.95}, {"date": "2024-12-23", "open": 259.25, "high": 275.08, "low": 252.95, "close": 262.42}, {"date": "2024-12-24", "open": 259.61, "high": 264.46, "low": 256.31, "close": 258.99}, {"date": "2024-12-25", "open": 259.61, "high": 264.46, "low": 256.31, "close": 258.99}, {"date": "2024-12-26", "open": 258, "high": 263.88, "low": 245.42, "close": 246.96}, {"date": "2024-12-27", "open": 246.03, "high": 251.77, "low": 246.03, "close": 247.13}, {"date": "2024-12-30", "open": 247.85, "high": 250.97, "low": 243.92, "close": 245.71}, {"date": "2024-12-31", "open": 245.9, "high": 274.19, "low": 245.63, "close": 265.31}, {"date": "2025-01-01", "open": 265.9, "high": 274, "low": 258.95, "close": 272.95}, {"date": "2025-01-02", "open": 271.65, "high": 275, "low": 265.3, "close": 267.55}, {"date": "2025-01-03", "open": 267, "high": 273.9, "low": 263.7, "close": 269.35}, {"date": "2025-01-06", "open": 267.8, "high": 267.8, "low": 251, "close": 252.3}, {"date": "2025-01-07", "open": 252, "high": 259, "low": 251.65, "close": 253.5}, {"date": "2025-01-08", "open": 258.5, "high": 258.5, "low": 246.25, "close": 249.95}, {"date": "2025-01-09", "open": 249, "high": 255, "low": 241.55, "close": 243.8}, {"date": "2025-01-10", "open": 244.85, "high": 244.85, "low": 236.15, "close": 242.4}, {"date": "2025-01-13", "open": 242, "high": 247.9, "low": 230, "close": 233.4}, {"date": "2025-01-14", "open": 231.2, "high": 237.4, "low": 231.2, "close": 235.65}, {"date": "2025-01-15", "open": 236.2, "high": 239.05, "low": 229.55, "close": 233.7}, {"date": "2025-01-16", "open": 238.85, "high": 240.9, "low": 235.25, "close": 237.3}, {"date": "2025-01-17", "open": 235.35, "high": 239.4, "low": 235.35, "close": 236.45}, {"date": "2025-01-20", "open": 237.4, "high": 241.95, "low": 236.85, "close": 238.55}, {"date": "2025-01-21", "open": 239.4, "high": 240.65, "low": 233.2, "close": 234.05}, {"date": "2025-01-22", "open": 238.9, "high": 238.95, "low": 230.05, "close": 231}, {"date": "2025-01-23", "open": 234.75, "high": 242.3, "low": 232, "close": 238.8}, {"date": "2025-01-24", "open": 238.8, "high": 244.65, "low": 236, "close": 239.2}, {"date": "2025-01-27", "open": 235, "high": 235.65, "low": 225.7, "close": 229.55}, {"date": "2025-01-28", "open": 234.05, "high": 234.1, "low": 223.9, "close": 225.95}, {"date": "2025-01-29", "open": 224, "high": 233.85, "low": 224, "close": 230.15}, {"date": "2025-01-30", "open": 228, "high": 240.15, "low": 228, "close": 235.8}, {"date": "2025-01-31", "open": 238.65, "high": 241, "low": 236, "close": 238.6}, {"date": "2025-02-03", "open": 243.8, "high": 246.8, "low": 233, "close": 234.18}, {"date": "2025-02-04", "open": 238.66, "high": 243, "low": 237.43, "close": 241.21}, {"date": "2025-02-05", "open": 244.4, "high": 244.4, "low": 239.99, "close": 242.56}, {"date": "2025-02-06", "open": 246.9, "high": 246.9, "low": 236.1, "close": 237.6}, {"date": "2025-02-07", "open": 240, "high": 240.17, "low": 232.8, "close": 234.92}, {"date": "2025-02-10", "open": 236.97, "high": 238.47, "low": 229.96, "close": 230.36}, {"date": "2025-02-11", "open": 232.33, "high": 233.27, "low": 223.37, "close": 224.93}, {"date": "2025-02-12", "open": 223.09, "high": 229.08, "low": 216.05, "close": 227.22}, {"date": "2025-02-13", "open": 233.57, "high": 233.57, "low": 221.99, "close": 228.26}, {"date": "2025-02-14", "open": 230, "high": 230, "low": 211, "close": 216.41}, {"date": "2025-02-17", "open": 218, "high": 218, "low": 207.1, "close": 210.43}, {"date": "2025-02-18", "open": 212.37, "high": 213.09, "low": 208, "close": 210.46}, {"date": "2025-02-19", "open": 211, "high": 215, "low": 208.1, "close": 214.56}, {"date": "2025-02-20", "open": 214.45, "high": 230.17, "low": 214.45, "close": 225.34}, {"date": "2025-02-21", "open": 223.1, "high": 228.73, "low": 217, "close": 219.6}, {"date": "2025-02-24", "open": 222, "high": 223.95, "low": 215.21, "close": 222.21}, {"date": "2025-02-25", "open": 224.9, "high": 227.96, "low": 220.81, "close": 223.28}, {"date": "2025-02-27", "open": 227.6, "high": 227.6, "low": 218, "close": 220.04}, {"date": "2025-02-28", "open": 219.9, "high": 220, "low": 202.99, "close": 208.97}, {"date": "2025-03-03", "open": 215.9, "high": 221, "low": 201.01, "close": 206.64}, {"date": "2025-03-04", "open": 41.99, "high": 47.9, "low": 40.91, "close": 46.47}, {"date": "2025-03-05", "open": 45.95, "high": 47.79, "low": 43.95, "close": 46.91}, {"date": "2025-03-06", "open": 46.2, "high": 46.99, "low": 45.47, "close": 46.04}, {"date": "2025-03-07", "open": 46.04, "high": 47.05, "low": 44.6, "close": 46}, {"date": "2025-03-10", "open": 46, "high": 46.8, "low": 41.31, "close": 46.19}, {"date": "2025-03-11", "open": 44.8, "high": 45.97, "low": 42.9, "close": 43.8}, {"date": "2025-03-12", "open": 44.2, "high": 44.2, "low": 37.62, "close": 40}, {"date": "2025-03-13", "open": 40, "high": 40.75, "low": 37, "close": 37.54}, {"date": "2025-03-17", "open": 37.94, "high": 39.66, "low": 36.01, "close": 38.85}, {"date": "2025-03-18", "open": 39.49, "high": 41.7, "low": 39.22, "close": 40.28}, {"date": "2025-03-19", "open": 40.98, "high": 41.73, "low": 39, "close": 40.2}, {"date": "2025-03-20", "open": 40.51, "high": 41.5, "low": 40.05, "close": 40.65}, {"date": "2025-03-21", "open": 40.88, "high": 41.73, "low": 40.45, "close": 41.62}, {"date": "2025-03-24", "open": 42.01, "high": 42.45, "low": 39, "close": 39.72}, {"date": "2025-03-25", "open": 40, "high": 40.79, "low": 37, "close": 38.05}, {"date": "2025-03-26", "open": 38.53, "high": 40.35, "low": 35.8, "close": 36.24}, {"date": "2025-03-27", "open": 36.24, "high": 38.75, "low": 34.74, "close": 35.04}, {"date": "2025-03-28", "open": 36, "high": 36.5, "low": 35.07, "close": 35.44}, {"date": "2025-04-01", "open": 35.44, "high": 38.45, "low": 35, "close": 37.34}, {"date": "2025-04-02", "open": 37.34, "high": 39.99, "low": 36.32, "close": 39.53}, {"date": "2025-04-03", "open": 38.4, "high": 38.95, "low": 34.7, "close": 35.87}, {"date": "2025-04-04", "open": 36.4, "high": 37.99, "low": 35.6, "close": 37.08}, {"date": "2025-04-07", "open": 35.69, "high": 35.9, "low": 33.61, "close": 34.49}, {"date": "2025-04-08", "open": 35, "high": 36.33, "low": 34.1, "close": 35.17}, {"date": "2025-04-09", "open": 34.31, "high": 34.65, "low": 33.91, "close": 34.04}, {"date": "2025-04-11", "open": 35, "high": 37, "low": 35, "close": 36.59}, {"date": "2025-04-15", "open": 37.15, "high": 39.5, "low": 37.15, "close": 39.04}, {"date": "2025-04-16", "open": 39.5, "high": 40.44, "low": 39.23, "close": 40.15}, {"date": "2025-04-17", "open": 40.86, "high": 41.03, "low": 40.04, "close": 40.79}, {"date": "2025-04-21", "open": 40.79, "high": 41.48, "low": 39.8, "close": 40.19}, {"date": "2025-04-22", "open": 40.49, "high": 41.91, "low": 39.1, "close": 39.67}, {"date": "2025-04-23", "open": 40.38, "high": 40.6, "low": 38.01, "close": 38.96}, {"date": "2025-04-24", "open": 39, "high": 40, "low": 38.41, "close": 39.78}, {"date": "2025-04-25", "open": 39.78, "high": 39.78, "low": 38.21, "close": 38.84}, {"date": "2025-04-28", "open": 39.48, "high": 39.48, "low": 36.99, "close": 37.62}, {"date": "2025-04-29", "open": 38.21, "high": 39.09, "low": 38.07, "close": 38.62}, {"date": "2025-04-30", "open": 39.4, "high": 39.4, "low": 36.6, "close": 36.99}, {"date": "2025-05-02", "open": 36.65, "high": 37.99, "low": 35.98, "close": 36.73}, {"date": "2025-05-05", "open": 37.45, "high": 37.74, "low": 36.58, "close": 37.22}, {"date": "2025-05-06", "open": 36.85, "high": 37.79, "low": 35.1, "close": 35.73}, {"date": "2025-05-07", "open": 35, "high": 36.2, "low": 32.7, "close": 35.67}, {"date": "2025-05-08", "open": 36.4, "high": 37.24, "low": 34.5, "close": 34.75}, {"date": "2025-05-09", "open": 34.7, "high": 36.85, "low": 34.35, "close": 35.81}, {"date": "2025-05-12", "open": 36.55, "high": 40, "low": 36, "close": 39.93}, {"date": "2025-05-13", "open": 40.48, "high": 40.48, "low": 38.98, "close": 39.32}, {"date": "2025-05-14", "open": 40.82, "high": 40.88, "low": 39.33, "close": 39.76}, {"date": "2025-05-15", "open": 39.24, "high": 40.49, "low": 35.89, "close": 37.04}, {"date": "2025-05-16", "open": 37.7, "high": 37.99, "low": 36.91, "close": 37.21}, {"date": "2025-05-19", "open": 37.21, "high": 37.9, "low": 36.75, "close": 36.95}, {"date": "2025-05-20", "open": 37.8, "high": 39.89, "low": 37.5, "close": 38.75}, {"date": "2025-05-21", "open": 39.4, "high": 39.4, "low": 37.5, "close": 38.26}, {"date": "2025-05-22", "open": 38.26, "high": 39.89, "low": 37.5, "close": 38.47}, {"date": "2025-05-23", "open": 38.66, "high": 39.99, "low": 38.23, "close": 39.3}, {"date": "2025-05-26", "open": 39.1, "high": 40.69, "low": 39.1, "close": 40.13}, {"date": "2025-05-27", "open": 41.87, "high": 42.8, "low": 40.37, "close": 42.6}, {"date": "2025-05-28", "open": 43.15, "high": 43.15, "low": 41.02, "close": 41.28}, {"date": "2025-05-29", "open": 41.91, "high": 41.91, "low": 40.4, "close": 40.85}, {"date": "2025-05-30", "open": 42.71, "high": 42.9, "low": 39.02, "close": 39.57}, {"date": "2025-06-02", "open": 39, "high": 39.39, "low": 37.36, "close": 39.05}, {"date": "2025-06-03", "open": 39.73, "high": 39.73, "low": 38.15, "close": 38.29}, {"date": "2025-06-04", "open": 38.5, "high": 39.68, "low": 38, "close": 39.46}, {"date": "2025-06-05", "open": 39.9, "high": 40.24, "low": 38.3, "close": 38.94}, {"date": "2025-06-06", "open": 39.7, "high": 39.83, "low": 38.17, "close": 38.87}, {"date": "2025-06-09", "open": 39, "high": 41.34, "low": 39, "close": 40.9}, {"date": "2025-06-10", "open": 40.8, "high": 40.98, "low": 39.75, "close": 40.52}, {"date": "2025-06-11", "open": 41.1, "high": 43.68, "low": 40.65, "close": 42.54}, {"date": "2025-06-12", "open": 43.4, "high": 43.4, "low": 39.05, "close": 40.09}, {"date": "2025-06-13", "open": 39.89, "high": 41.31, "low": 38.6, "close": 39.12}, {"date": "2025-06-16", "open": 39.88, "high": 39.88, "low": 38.5, "close": 39.12}, {"date": "2025-06-17", "open": 38.7, "high": 40.49, "low": 38.25, "close": 38.65}, {"date": "2025-06-18", "open": 39.4, "high": 40.24, "low": 38.15, "close": 39.58}, {"date": "2025-06-19", "open": 39.01, "high": 39.97, "low": 37.76, "close": 38.04}, {"date": "2025-06-20", "open": 38.33, "high": 39.55, "low": 37.51, "close": 39.22}, {"date": "2025-06-23", "open": 39.11, "high": 39.22, "low": 37.05, "close": 37.38}, {"date": "2025-06-24", "open": 38.69, "high": 38.87, "low": 37.51, "close": 37.75}, {"date": "2025-06-25", "open": 37.95, "high": 38.58, "low": 37.41, "close": 38.22}, {"date": "2025-06-26", "open": 38.39, "high": 38.6, "low": 37.73, "close": 38.15}, {"date": "2025-06-27", "open": 38.15, "high": 39.89, "low": 37.85, "close": 38.29}, {"date": "2025-06-30", "open": 39.04, "high": 40.5, "low": 38.15, "close": 38.32}, {"date": "2025-07-01", "open": 38.7, "high": 38.9, "low": 37.79, "close": 38.27}, {"date": "2025-07-02", "open": 38.5, "high": 39.15, "low": 37.96, "close": 38.35}, {"date": "2025-07-03", "open": 39.1, "high": 39.1, "low": 38.05, "close": 38.31}, {"date": "2025-07-04", "open": 38.03, "high": 38.75, "low": 38.03, "close": 38.57}, {"date": "2025-07-07", "open": 38.8, "high": 38.8, "low": 37.7, "close": 38}, {"date": "2025-07-08", "open": 38.4, "high": 38.4, "low": 37.5, "close": 38.12}, {"date": "2025-07-09", "open": 37.7, "high": 38.32, "low": 37.7, "close": 38.05}, {"date": "2025-07-10", "open": 38.4, "high": 38.4, "low": 37.5, "close": 37.79}, {"date": "2025-07-11", "open": 37.97, "high": 38.45, "low": 36.65, "close": 38.08}, {"date": "2025-07-14", "open": 38.4, "high": 38.4, "low": 37.15, "close": 37.45}, {"date": "2025-07-15", "open": 37.45, "high": 37.85, "low": 36.95, "close": 37.01}, {"date": "2025-07-16", "open": 37.29, "high": 37.48, "low": 36.55, "close": 36.94}, {"date": "2025-07-17", "open": 37.4, "high": 37.59, "low": 36.4, "close": 36.91}, {"date": "2025-07-18", "open": 36.9, "high": 37.4, "low": 35.9, "close": 36.2}, {"date": "2025-07-21", "open": 36.38, "high": 37.47, "low": 34.95, "close": 35.91}, {"date": "2025-07-22", "open": 36.15, "high": 36.4, "low": 35.5, "close": 36.03}, {"date": "2025-07-23", "open": 36.14, "high": 37.5, "low": 35.86, "close": 36.52}, {"date": "2025-07-24", "open": 36.55, "high": 37.5, "low": 36.2, "close": 37.25}, {"date": "2025-07-25", "open": 37.26, "high": 38.99, "low": 36.02, "close": 36.13}, {"date": "2025-07-28", "open": 36.6, "high": 37.73, "low": 35.45, "close": 35.97}, {"date": "2025-07-29", "open": 36.69, "high": 37.65, "low": 36.26, "close": 36.59}, {"date": "2025-07-30", "open": 36.4, "high": 36.95, "low": 36.15, "close": 36.75}, {"date": "2025-07-31", "open": 36.11, "high": 36.4, "low": 35.17, "close": 35.33}, {"date": "2025-08-01", "open": 35.35, "high": 35.81, "low": 34.29, "close": 35.04}, {"date": "2025-08-04", "open": 35, "high": 36.18, "low": 34.22, "close": 35.88}, {"date": "2025-08-05", "open": 35.87, "high": 35.87, "low": 34.95, "close": 35.03}, {"date": "2025-08-06", "open": 35.28, "high": 35.3, "low": 33.97, "close": 34.06}, {"date": "2025-08-07", "open": 33.9, "high": 34.65, "low": 33.89, "close": 34.31}, {"date": "2025-08-08", "open": 34.65, "high": 34.65, "low": 33.01, "close": 33.72}, {"date": "2025-08-11", "open": 33.72, "high": 34.15, "low": 33.5, "close": 33.7}, {"date": "2025-08-12", "open": 33.7, "high": 34.59, "low": 31.37, "close": 32.13}, {"date": "2025-08-13", "open": 32, "high": 33.2, "low": 32, "close": 32.83}, {"date": "2025-08-14", "open": 33.89, "high": 33.89, "low": 32, "close": 32.78}, {"date": "2025-08-18", "open": 32.55, "high": 37.88, "low": 32.55, "close": 35.07}, {"date": "2025-08-19", "open": 35.75, "high": 35.75, "low": 34.26, "close": 34.62}, {"date": "2025-08-20", "open": 34.6, "high": 35.18, "low": 33.25, "close": 33.82}, {"date": "2025-08-21", "open": 33.5, "high": 34.23, "low": 33.35, "close": 33.52}, {"date": "2025-08-22", "open": 33.9, "high": 34.7, "low": 33.05, "close": 33.38}, {"date": "2025-08-25", "open": 33.8, "high": 34.08, "low": 32.86, "close": 33.07}, {"date": "2025-08-26", "open": 33.07, "high": 33.07, "low": 31.9, "close": 32.07}, {"date": "2025-08-28", "open": 32.5, "high": 32.76, "low": 31.75, "close": 31.86}, {"date": "2025-08-29", "open": 31.87, "high": 32.29, "low": 31.2, "close": 31.52}, {"date": "2025-09-01", "open": 31.51, "high": 31.85, "low": 30.01, "close": 30.57}, {"date": "2025-09-02", "open": 30.95, "high": 31.69, "low": 30.85, "close": 31.07}, {"date": "2025-09-03", "open": 31.43, "high": 32, "low": 30.88, "close": 31.67}, {"date": "2025-09-04", "open": 32.19, "high": 32.19, "low": 31.39, "close": 31.84}, {"date": "2025-09-05", "open": 31.84, "high": 32.25, "low": 30.7, "close": 31.69}, {"date": "2025-09-08", "open": 31.5, "high": 32.85, "low": 31.06, "close": 32.29}, {"date": "2025-09-09", "open": 32.65, "high": 32.88, "low": 30.95, "close": 31.3}, {"date": "2025-09-10", "open": 32.99, "high": 37.56, "low": 32.99, "close": 37.56}, {"date": "2025-09-11", "open": 40.57, "high": 41.68, "low": 38, "close": 38.27}, {"date": "2025-09-12", "open": 38.27, "high": 39.3, "low": 37.01, "close": 38.54}, {"date": "2025-09-15", "open": 39.3, "high": 39.81, "low": 37.2, "close": 38.38}, {"date": "2025-09-16", "open": 39.14, "high": 39.21, "low": 37.5, "close": 37.92}, {"date": "2025-09-17", "open": 38.1, "high": 38.69, "low": 36.59, "close": 37.01}, {"date": "2025-09-18", "open": 37.03, "high": 39.99, "low": 37.03, "close": 38.25}, {"date": "2025-09-19", "open": 38.32, "high": 39.13, "low": 37.5, "close": 37.96}, {"date": "2025-09-22", "open": 37.51, "high": 38.69, "low": 35, "close": 35.66}, {"date": "2025-09-23", "open": 35.51, "high": 36.28, "low": 33.36, "close": 33.95}, {"date": "2025-09-24", "open": 33.96, "high": 34.84, "low": 33.4, "close": 33.66}, {"date": "2025-09-25", "open": 34, "high": 34, "low": 33, "close": 33.16}, {"date": "2025-09-26", "open": 32.7, "high": 33.4, "low": 32.5, "close": 32.95}, {"date": "2025-09-29", "open": 33.38, "high": 34.5, "low": 32.73, "close": 34.31}, {"date": "2025-09-30", "open": 34.6, "high": 36, "low": 34.37, "close": 35.25}, {"date": "2025-10-01", "open": 35.4, "high": 35.6, "low": 34.86, "close": 35.07}, {"date": "2025-10-03", "open": 35.24, "high": 35.26, "low": 34.4, "close": 34.61}, {"date": "2025-10-06", "open": 34.6, "high": 36.1, "low": 34.25, "close": 35.65}, {"date": "2025-10-07", "open": 35.79, "high": 36.5, "low": 34.75, "close": 35.53}, {"date": "2025-10-08", "open": 36.2, "high": 36.2, "low": 35.34, "close": 35.83}, {"date": "2025-10-09", "open": 35.83, "high": 37.8, "low": 35.52, "close": 36.75}, {"date": "2025-10-10", "open": 36.75, "high": 38.24, "low": 36.7, "close": 37.84}, {"date": "2025-10-13", "open": 38, "high": 38.83, "low": 36.25, "close": 36.94}, {"date": "2025-10-14", "open": 37.3, "high": 37.3, "low": 35.8, "close": 36.26}, {"date": "2025-10-15", "open": 35.85, "high": 38.95, "low": 35.85, "close": 36.25}, {"date": "2025-10-16", "open": 36.55, "high": 37.4, "low": 36.55, "close": 37.06}, {"date": "2025-10-17", "open": 37.3, "high": 38.8, "low": 36.93, "close": 37.51}, {"date": "2025-10-20", "open": 37.6, "high": 37.75, "low": 36.98, "close": 37.25}, {"date": "2025-10-21", "open": 37.25, "high": 38.9, "low": 37.2, "close": 37.34}, {"date": "2025-10-22", "open": 37.25, "high": 38.9, "low": 37.2, "close": 37.34}, {"date": "2025-10-23", "open": 43, "high": 44.8, "low": 42.25, "close": 44.8}, {"date": "2025-10-24", "open": 47.5, "high": 48.37, "low": 42.1, "close": 42.84}, {"date": "2025-10-27", "open": 42.4, "high": 42.62, "low": 39.66, "close": 40}, {"date": "2025-10-28", "open": 40.55, "high": 44.7, "low": 39.76, "close": 41.23}, {"date": "2025-10-29", "open": 41.8, "high": 42.98, "low": 40.15, "close": 41.07}, {"date": "2025-10-30", "open": 41.79, "high": 41.79, "low": 40.6, "close": 41.24}, {"date": "2025-10-31", "open": 41, "high": 43.89, "low": 41, "close": 42.06}, {"date": "2025-11-03", "open": 42.79, "high": 42.79, "low": 40.5, "close": 40.91}, {"date": "2025-11-04", "open": 40.87, "high": 41.35, "low": 39.5, "close": 39.75}, {"date": "2025-11-05", "open": 40.87, "high": 41.35, "low": 39.5, "close": 39.75}, {"date": "2025-11-06", "open": 39.75, "high": 40.11, "low": 37.55, "close": 38.3}, {"date": "2025-11-07", "open": 38.7, "high": 43.4, "low": 38.2, "close": 41.41}, {"date": "2025-11-10", "open": 41.99, "high": 43.4, "low": 41.1, "close": 41.85}, {"date": "2025-11-11", "open": 42.05, "high": 42.06, "low": 40.06, "close": 41.15}, {"date": "2025-11-12", "open": 41.99, "high": 42.9, "low": 39.99, "close": 41.93}, {"date": "2025-11-13", "open": 41.95, "high": 42.44, "low": 40.73, "close": 40.86}, {"date": "2025-11-14", "open": 40.66, "high": 41.89, "low": 40.51, "close": 40.85}, {"date": "2025-11-17", "open": 40.84, "high": 41.79, "low": 40.71, "close": 40.98}, {"date": "2025-11-18", "open": 41.1, "high": 42.2, "low": 41.1, "close": 42.04}, {"date": "2025-11-19", "open": 42.19, "high": 46, "low": 41.35, "close": 44.16}, {"date": "2025-11-20", "open": 44.38, "high": 44.48, "low": 42.22, "close": 43.04}, {"date": "2025-11-21", "open": 43.8, "high": 46.7, "low": 42.75, "close": 45.94}, {"date": "2025-11-24", "open": 45.16, "high": 47.23, "low": 43.31, "close": 43.7}, {"date": "2025-11-25", "open": 44.13, "high": 45, "low": 42.15, "close": 44.54}, {"date": "2025-11-26", "open": 44.99, "high": 46.49, "low": 43.82, "close": 44.55}, {"date": "2025-11-27", "open": 44.55, "high": 45.6, "low": 44.1, "close": 44.28}, {"date": "2025-11-28", "open": 43.6, "high": 47.6, "low": 43.6, "close": 46.56}, {"date": "2025-12-01", "open": 46.11, "high": 47.79, "low": 45.6, "close": 46.19}, {"date": "2025-12-02", "open": 46.46, "high": 46.76, "low": 44.78, "close": 45.27}, {"date": "2025-12-03", "open": 46, "high": 46.45, "low": 44.97, "close": 45.8}, {"date": "2026-03-09", "open": 43.49, "high": 43.5, "low": 41, "close": 42.6}, {"date": "2026-03-10", "open": 44, "high": 46.49, "low": 43.02, "close": 43.42}, {"date": "2026-03-11", "open": 45.7, "high": 46.78, "low": 42, "close": 44.71}, {"date": "2026-03-12", "open": 44, "high": 44.55, "low": 42.8, "close": 43.1}, {"date": "2026-03-13", "open": 42.83, "high": 44.94, "low": 42.04, "close": 43.64}, {"date": "2026-03-16", "open": 44.4, "high": 49.5, "low": 38.32, "close": 45.94}, {"date": "2026-03-17", "open": 48.5, "high": 49.45, "low": 45.12, "close": 46.22}, {"date": "2026-03-18", "open": 47, "high": 47.02, "low": 44.05, "close": 44.38}, {"date": "2026-03-19", "open": 44.5, "high": 45.58, "low": 43.5, "close": 43.57}, {"date": "2026-03-20", "open": 43, "high": 44.96, "low": 43, "close": 43.27}, {"date": "2026-03-23", "open": 42.09, "high": 45.12, "low": 42.07, "close": 42.8}, {"date": "2026-03-24", "open": 44.77, "high": 51.36, "low": 43.07, "close": 44.69}, {"date": "2026-03-25", "open": 43.96, "high": 46.38, "low": 43.5, "close": 44.14}, {"date": "2026-03-26", "open": 43.96, "high": 46.38, "low": 43.5, "close": 44.14}, {"date": "2026-03-27", "open": 44, "high": 45.56, "low": 42.1, "close": 42.45}, {"date": "2026-03-30", "open": 42.46, "high": 42.99, "low": 39.3, "close": 41.03}, {"date": "2026-03-31", "open": 42.46, "high": 42.99, "low": 39.3, "close": 41.03}, {"date": "2026-04-01", "open": 45.49, "high": 47.01, "low": 43, "close": 43.89}, {"date": "2026-04-02", "open": 43.47, "high": 46, "low": 43, "close": 45.79}, {"date": "2026-04-03", "open": 43.47, "high": 46, "low": 43, "close": 45.79}, {"date": "2026-04-06", "open": 45.79, "high": 49.4, "low": 43.74, "close": 48.01}, {"date": "2026-04-07", "open": 48.99, "high": 48.99, "low": 46.23, "close": 47.06}, {"date": "2026-04-08", "open": 49, "high": 50.13, "low": 47.26, "close": 49.25}, {"date": "2026-04-09", "open": 49, "high": 50, "low": 48.5, "close": 49.5}, {"date": "2026-04-10", "open": 50, "high": 51.69, "low": 48.01, "close": 49.65}, {"date": "2026-04-13", "open": 47.55, "high": 51.59, "low": 47.43, "close": 49.81}, {"date": "2026-04-14", "open": 47.55, "high": 51.59, "low": 47.43, "close": 49.81}, {"date": "2026-04-15", "open": 49.81, "high": 51.49, "low": 49.81, "close": 50.7}, {"date": "2026-04-16", "open": 52.2, "high": 52.2, "low": 50.16, "close": 50.81}, {"date": "2026-04-17", "open": 51.81, "high": 54.95, "low": 51.5, "close": 53.04}, {"date": "2026-04-20", "open": 54.95, "high": 55.51, "low": 50.5, "close": 51.05}, {"date": "2026-04-21", "open": 49.75, "high": 54.44, "low": 49.75, "close": 53.82}, {"date": "2026-04-22", "open": 54.9, "high": 54.9, "low": 52.27, "close": 53.68}, {"date": "2026-04-23", "open": 53.68, "high": 58, "low": 53.31, "close": 55.77}, {"date": "2026-04-24", "open": 56.5, "high": 57.1, "low": 52.31, "close": 55.67}, {"date": "2026-04-27", "open": 63.5, "high": 63.5, "low": 57.32, "close": 58.43}, {"date": "2026-04-28", "open": 59, "high": 59.19, "low": 56.21, "close": 56.86}, {"date": "2026-04-29", "open": 56.86, "high": 58.29, "low": 55, "close": 55.99}, {"date": "2026-04-30", "open": 56.27, "high": 57.69, "low": 55.25, "close": 57.19}, {"date": "2026-05-01", "open": 56.27, "high": 57.69, "low": 55.25, "close": 57.19}, {"date": "2026-05-04", "open": 57.2, "high": 58.41, "low": 56.4, "close": 56.68}, {"date": "2026-05-05", "open": 56.95, "high": 57.39, "low": 55.5, "close": 56.92}, {"date": "2026-05-06", "open": 57.2, "high": 60, "low": 56.79, "close": 59.01}, {"date": "2026-05-07", "open": 58.1, "high": 63.5, "low": 58, "close": 62.93}, {"date": "2026-05-08", "open": 63.5, "high": 64.7, "low": 61.25, "close": 62.38}, {"date": "2026-05-11", "open": 63, "high": 65.4, "low": 61.75, "close": 62.39}, {"date": "2026-05-12", "open": 61.67, "high": 62.79, "low": 57.5, "close": 58.2}, {"date": "2026-05-13", "open": 58.5, "high": 62, "low": 58, "close": 61.18}, {"date": "2026-05-14", "open": 61.4, "high": 62.48, "low": 58.2, "close": 60.36}, {"date": "2026-05-15", "open": 60.99, "high": 66.7, "low": 59.91, "close": 62.26}, {"date": "2026-05-18", "open": 61.55, "high": 62.24, "low": 59.18, "close": 60.43}, {"date": "2026-05-19", "open": 60.43, "high": 62.59, "low": 60.02, "close": 60.41}, {"date": "2026-05-20", "open": 60.41, "high": 60.5, "low": 59.02, "close": 59.66}, {"date": "2026-05-21", "open": 59.75, "high": 60.68, "low": 57.62, "close": 57.82}, {"date": "2026-05-22", "open": 58.05, "high": 60.15, "low": 57.15, "close": 57.93}, {"date": "2026-05-25", "open": 58.93, "high": 59.05, "low": 57, "close": 58.69}, {"date": "2026-05-26", "open": 58, "high": 62.9, "low": 58, "close": 61.12}, {"date": "2026-05-27", "open": 62, "high": 63, "low": 60.14, "close": 60.9}, {"date": "2026-05-28", "open": 62, "high": 63, "low": 60.14, "close": 60.9}, {"date": "2026-05-29", "open": 60.6, "high": 62.23, "low": 59, "close": 60.25}, {"date": "2026-06-01", "open": 60.7, "high": 62.18, "low": 48.2, "close": 48.74}, {"date": "2026-06-02", "open": 48.7, "high": 49.8, "low": 46.56, "close": 48.18}, {"date": "2026-06-03", "open": 49.08, "high": 49.7, "low": 46.51, "close": 47.72}, {"date": "2026-06-04", "open": 47.49, "high": 50.25, "low": 47.46, "close": 48.9}, {"date": "2026-06-05", "open": 49, "high": 51.27, "low": 49, "close": 49.75}, {"date": "2026-06-08", "open": 49, "high": 49.77, "low": 47.01, "close": 47.76}, {"date": "2026-06-09", "open": 48, "high": 48.71, "low": 47.51, "close": 48.43}, {"date": "2026-06-10", "open": 48.78, "high": 48.78, "low": 46.1, "close": 46.41}, {"date": "2026-06-11", "open": 46.5, "high": 46.65, "low": 44.05, "close": 45.2}, {"date": "2026-06-12", "open": 46.2, "high": 49.6, "low": 46, "close": 48.85}, {"date": "2026-06-15", "open": 49.99, "high": 50.49, "low": 48.22, "close": 48.81}, {"date": "2026-06-16", "open": 49.89, "high": 51.75, "low": 48.26, "close": 51.37}, {"date": "2026-06-17", "open": 52.74, "high": 52.74, "low": 50.34, "close": 51.16}, {"date": "2026-06-18", "open": 52.24, "high": 52.24, "low": 50.75, "close": 51.53}, {"date": "2026-06-19", "open": 51.47, "high": 53.29, "low": 49.9, "close": 51.85}, {"date": "2026-06-22", "open": 52.79, "high": 53.24, "low": 51.9, "close": 52.12}, {"date": "2026-06-23", "open": 52.01, "high": 52.99, "low": 50.9, "close": 51.09}, {"date": "2026-06-24", "open": 51.49, "high": 51.99, "low": 50.01, "close": 50.5}, {"date": "2026-06-25", "open": 50.93, "high": 51.8, "low": 50.06, "close": 50.11}, {"date": "2026-06-26", "open": 50.93, "high": 51.8, "low": 50.06, "close": 50.11}, {"date": "2026-06-29", "open": 50.39, "high": 50.59, "low": 48.65, "close": 49.34}, {"date": "2026-06-30", "open": 49.82, "high": 49.82, "low": 48.4, "close": 48.87}, {"date": "2026-07-01", "open": 48.56, "high": 53.49, "low": 48.56, "close": 50.31}, {"date": "2026-07-02", "open": 50.97, "high": 52.95, "low": 49.16, "close": 52.19}, {"date": "2026-07-03", "open": 52.19, "high": 53.49, "low": 50.8, "close": 51.12}, {"date": "2026-07-06", "open": 50.55, "high": 51.88, "low": 50.5, "close": 50.81}, {"date": "2026-07-07", "open": 50.55, "high": 51.46, "low": 49.5, "close": 50}, {"date": "2026-07-08", "open": 50.7, "high": 51, "low": 48, "close": 48.65}, {"date": "2026-07-09", "open": 49.01, "high": 50.67, "low": 47.71, "close": 49.92}, {"date": "2026-07-10", "open": 50.42, "high": 51.69, "low": 50.2, "close": 50.82}, {"date": "2026-07-13", "open": 50.85, "high": 52.5, "low": 50.21, "close": 51.85}, {"date": "2026-07-14", "open": 52.45, "high": 52.45, "low": 50.2, "close": 50.6}, {"date": "2026-07-15", "open": 50.3, "high": 53.2, "low": 49.6, "close": 52.48}, {"date": "2026-07-16", "open": 51.56, "high": 55.54, "low": 51.56, "close": 53.6}, {"date": "2026-07-17", "open": 54.3, "high": 55.5, "low": 52.04, "close": 52.62}, {"date": "2026-07-20", "open": 52.36, "high": 53.8, "low": 52.36, "close": 52.82}]